[
    {
        "Country name": "Finland",
        "HappinessRank": "1",
        "HappinesScore": "7.842",
        "GDP_per _capita": "10.775",
        "SocialSupport": "0.954",
        "Healthy life expectancy": "72",
        "Freedom to make life choices": "0.949",
        "Generosity": "-0.098",
        "Perceptions of corruption": "0.186"
    },
    {
        "Country name": "Denmark",
        "HappinessRank": "2",
        "HappinesScore": "7.62",
        "GDP_per _capita": "10.933",
        "SocialSupport": "0.954",
        "Healthy life expectancy": "72.7",
        "Freedom to make life choices": "0.946",
        "Generosity": "0.03",
        "Perceptions of corruption": "0.179"
    },
    {
        "Country name": "Switzerland",
        "HappinessRank": "3",
        "HappinesScore": "7.571",
        "GDP_per _capita": "11.117",
        "SocialSupport": "0.942",
        "Healthy life expectancy": "74.4",
        "Freedom to make life choices": "0.919",
        "Generosity": "0.025",
        "Perceptions of corruption": "0.292"
    },
    {
        "Country name": "Iceland",
        "HappinessRank": "4",
        "HappinesScore": "7.554",
        "GDP_per _capita": "10.878",
        "SocialSupport": "0.983",
        "Healthy life expectancy": "73",
        "Freedom to make life choices": "0.955",
        "Generosity": "0.16",
        "Perceptions of corruption": "0.673"
    },
    {
        "Country name": "Netherlands",
        "HappinessRank": "5",
        "HappinesScore": "7.464",
        "GDP_per _capita": "10.932",
        "SocialSupport": "0.942",
        "Healthy life expectancy": "72.4",
        "Freedom to make life choices": "0.913",
        "Generosity": "0.175",
        "Perceptions of corruption": "0.338"
    },
    {
        "Country name": "Norway",
        "HappinessRank": "6",
        "HappinesScore": "7.392",
        "GDP_per _capita": "11.053",
        "SocialSupport": "0.954",
        "Healthy life expectancy": "73.3",
        "Freedom to make life choices": "0.96",
        "Generosity": "0.093",
        "Perceptions of corruption": "0.27"
    },
    {
        "Country name": "Sweden",
        "HappinessRank": "7",
        "HappinesScore": "7.363",
        "GDP_per _capita": "10.867",
        "SocialSupport": "0.934",
        "Healthy life expectancy": "72.7",
        "Freedom to make life choices": "0.945",
        "Generosity": "0.086",
        "Perceptions of corruption": "0.237"
    },
    {
        "Country name": "Luxembourg",
        "HappinessRank": "8",
        "HappinesScore": "7.324",
        "GDP_per _capita": "11.647",
        "SocialSupport": "0.908",
        "Healthy life expectancy": "72.6",
        "Freedom to make life choices": "0.907",
        "Generosity": "-0.034",
        "Perceptions of corruption": "0.386"
    },
    {
        "Country name": "New Zealand",
        "HappinessRank": "9",
        "HappinesScore": "7.277",
        "GDP_per _capita": "10.643",
        "SocialSupport": "0.948",
        "Healthy life expectancy": "73.4",
        "Freedom to make life choices": "0.929",
        "Generosity": "0.134",
        "Perceptions of corruption": "0.242"
    },
    {
        "Country name": "Austria",
        "HappinessRank": "10",
        "HappinesScore": "7.268",
        "GDP_per _capita": "10.906",
        "SocialSupport": "0.934",
        "Healthy life expectancy": "73.3",
        "Freedom to make life choices": "0.908",
        "Generosity": "0.042",
        "Perceptions of corruption": "0.481"
    },
    {
        "Country name": "Australia",
        "HappinessRank": "11",
        "HappinesScore": "7.183",
        "GDP_per _capita": "10.796",
        "SocialSupport": "0.94",
        "Healthy life expectancy": "73.9",
        "Freedom to make life choices": "0.914",
        "Generosity": "0.159",
        "Perceptions of corruption": "0.442"
    },
    {
        "Country name": "Israel",
        "HappinessRank": "12",
        "HappinesScore": "7.157",
        "GDP_per _capita": "10.575",
        "SocialSupport": "0.939",
        "Healthy life expectancy": "73.503",
        "Freedom to make life choices": "0.8",
        "Generosity": "0.031",
        "Perceptions of corruption": "0.753"
    },
    {
        "Country name": "Germany",
        "HappinessRank": "13",
        "HappinesScore": "7.155",
        "GDP_per _capita": "10.873",
        "SocialSupport": "0.903",
        "Healthy life expectancy": "72.5",
        "Freedom to make life choices": "0.875",
        "Generosity": "0.011",
        "Perceptions of corruption": "0.46"
    },
    {
        "Country name": "Canada",
        "HappinessRank": "14",
        "HappinesScore": "7.103",
        "GDP_per _capita": "10.776",
        "SocialSupport": "0.926",
        "Healthy life expectancy": "73.8",
        "Freedom to make life choices": "0.915",
        "Generosity": "0.089",
        "Perceptions of corruption": "0.415"
    },
    {
        "Country name": "Ireland",
        "HappinessRank": "15",
        "HappinesScore": "7.085",
        "GDP_per _capita": "11.342",
        "SocialSupport": "0.947",
        "Healthy life expectancy": "72.4",
        "Freedom to make life choices": "0.879",
        "Generosity": "0.077",
        "Perceptions of corruption": "0.363"
    },
    {
        "Country name": "Costa Rica",
        "HappinessRank": "16",
        "HappinesScore": "7.069",
        "GDP_per _capita": "9.88",
        "SocialSupport": "0.891",
        "Healthy life expectancy": "71.4",
        "Freedom to make life choices": "0.934",
        "Generosity": "-0.126",
        "Perceptions of corruption": "0.809"
    },
    {
        "Country name": "United Kingdom",
        "HappinessRank": "17",
        "HappinesScore": "7.064",
        "GDP_per _capita": "10.707",
        "SocialSupport": "0.934",
        "Healthy life expectancy": "72.5",
        "Freedom to make life choices": "0.859",
        "Generosity": "0.233",
        "Perceptions of corruption": "0.459"
    },
    {
        "Country name": "Czech Republic",
        "HappinessRank": "18",
        "HappinesScore": "6.965",
        "GDP_per _capita": "10.556",
        "SocialSupport": "0.947",
        "Healthy life expectancy": "70.807",
        "Freedom to make life choices": "0.858",
        "Generosity": "-0.208",
        "Perceptions of corruption": "0.868"
    },
    {
        "Country name": "United States",
        "HappinessRank": "19",
        "HappinesScore": "6.951",
        "GDP_per _capita": "11.023",
        "SocialSupport": "0.92",
        "Healthy life expectancy": "68.2",
        "Freedom to make life choices": "0.837",
        "Generosity": "0.098",
        "Perceptions of corruption": "0.698"
    },
    {
        "Country name": "Belgium",
        "HappinessRank": "20",
        "HappinesScore": "6.834",
        "GDP_per _capita": "10.823",
        "SocialSupport": "0.906",
        "Healthy life expectancy": "72.199",
        "Freedom to make life choices": "0.783",
        "Generosity": "-0.153",
        "Perceptions of corruption": "0.646"
    },
    {
        "Country name": "France",
        "HappinessRank": "21",
        "HappinesScore": "6.69",
        "GDP_per _capita": "10.704",
        "SocialSupport": "0.942",
        "Healthy life expectancy": "74",
        "Freedom to make life choices": "0.822",
        "Generosity": "-0.147",
        "Perceptions of corruption": "0.571"
    },
    {
        "Country name": "Bahrain",
        "HappinessRank": "22",
        "HappinesScore": "6.647",
        "GDP_per _capita": "10.669",
        "SocialSupport": "0.862",
        "Healthy life expectancy": "69.495",
        "Freedom to make life choices": "0.925",
        "Generosity": "0.089",
        "Perceptions of corruption": "0.722"
    },
    {
        "Country name": "Malta",
        "HappinessRank": "23",
        "HappinesScore": "6.602",
        "GDP_per _capita": "10.674",
        "SocialSupport": "0.931",
        "Healthy life expectancy": "72.2",
        "Freedom to make life choices": "0.927",
        "Generosity": "0.133",
        "Perceptions of corruption": "0.653"
    },
    {
        "Country name": "Taiwan Province of China",
        "HappinessRank": "24",
        "HappinesScore": "6.584",
        "GDP_per _capita": "10.871",
        "SocialSupport": "0.898",
        "Healthy life expectancy": "69.6",
        "Freedom to make life choices": "0.784",
        "Generosity": "-0.07",
        "Perceptions of corruption": "0.721"
    },
    {
        "Country name": "United Arab Emirates",
        "HappinessRank": "25",
        "HappinesScore": "6.561",
        "GDP_per _capita": "11.085",
        "SocialSupport": "0.844",
        "Healthy life expectancy": "67.333",
        "Freedom to make life choices": "0.932",
        "Generosity": "0.074",
        "Perceptions of corruption": "0.589"
    },
    {
        "Country name": "Saudi Arabia",
        "HappinessRank": "26",
        "HappinesScore": "6.494",
        "GDP_per _capita": "10.743",
        "SocialSupport": "0.891",
        "Healthy life expectancy": "66.603",
        "Freedom to make life choices": "0.877",
        "Generosity": "-0.149",
        "Perceptions of corruption": "0.684"
    },
    {
        "Country name": "Spain",
        "HappinessRank": "27",
        "HappinesScore": "6.491",
        "GDP_per _capita": "10.571",
        "SocialSupport": "0.932",
        "Healthy life expectancy": "74.7",
        "Freedom to make life choices": "0.761",
        "Generosity": "-0.081",
        "Perceptions of corruption": "0.745"
    },
    {
        "Country name": "Italy",
        "HappinessRank": "28",
        "HappinesScore": "6.483",
        "GDP_per _capita": "10.623",
        "SocialSupport": "0.88",
        "Healthy life expectancy": "73.8",
        "Freedom to make life choices": "0.693",
        "Generosity": "-0.084",
        "Perceptions of corruption": "0.866"
    },
    {
        "Country name": "Slovenia",
        "HappinessRank": "29",
        "HappinesScore": "6.461",
        "GDP_per _capita": "10.529",
        "SocialSupport": "0.948",
        "Healthy life expectancy": "71.4",
        "Freedom to make life choices": "0.949",
        "Generosity": "-0.101",
        "Perceptions of corruption": "0.806"
    },
    {
        "Country name": "Guatemala",
        "HappinessRank": "30",
        "HappinesScore": "6.435",
        "GDP_per _capita": "9.053",
        "SocialSupport": "0.813",
        "Healthy life expectancy": "64.958",
        "Freedom to make life choices": "0.906",
        "Generosity": "-0.038",
        "Perceptions of corruption": "0.775"
    },
    {
        "Country name": "Uruguay",
        "HappinessRank": "31",
        "HappinesScore": "6.431",
        "GDP_per _capita": "9.966",
        "SocialSupport": "0.925",
        "Healthy life expectancy": "69.1",
        "Freedom to make life choices": "0.896",
        "Generosity": "-0.092",
        "Perceptions of corruption": "0.59"
    },
    {
        "Country name": "Singapore",
        "HappinessRank": "32",
        "HappinesScore": "6.377",
        "GDP_per _capita": "11.488",
        "SocialSupport": "0.915",
        "Healthy life expectancy": "76.953",
        "Freedom to make life choices": "0.927",
        "Generosity": "-0.018",
        "Perceptions of corruption": "0.082"
    },
    {
        "Country name": "Kosovo",
        "HappinessRank": "33",
        "HappinesScore": "6.372",
        "GDP_per _capita": "9.318",
        "SocialSupport": "0.821",
        "Healthy life expectancy": "63.813",
        "Freedom to make life choices": "0.869",
        "Generosity": "0.257",
        "Perceptions of corruption": "0.917"
    },
    {
        "Country name": "Slovakia",
        "HappinessRank": "34",
        "HappinesScore": "6.331",
        "GDP_per _capita": "10.369",
        "SocialSupport": "0.936",
        "Healthy life expectancy": "69.201",
        "Freedom to make life choices": "0.766",
        "Generosity": "-0.124",
        "Perceptions of corruption": "0.911"
    },
    {
        "Country name": "Brazil",
        "HappinessRank": "35",
        "HappinesScore": "6.33",
        "GDP_per _capita": "9.577",
        "SocialSupport": "0.882",
        "Healthy life expectancy": "66.601",
        "Freedom to make life choices": "0.804",
        "Generosity": "-0.071",
        "Perceptions of corruption": "0.756"
    },
    {
        "Country name": "Mexico",
        "HappinessRank": "36",
        "HappinesScore": "6.317",
        "GDP_per _capita": "9.859",
        "SocialSupport": "0.831",
        "Healthy life expectancy": "68.597",
        "Freedom to make life choices": "0.862",
        "Generosity": "-0.147",
        "Perceptions of corruption": "0.799"
    },
    {
        "Country name": "Jamaica",
        "HappinessRank": "37",
        "HappinesScore": "6.309",
        "GDP_per _capita": "9.186",
        "SocialSupport": "0.877",
        "Healthy life expectancy": "67.5",
        "Freedom to make life choices": "0.89",
        "Generosity": "-0.137",
        "Perceptions of corruption": "0.884"
    },
    {
        "Country name": "Lithuania",
        "HappinessRank": "38",
        "HappinesScore": "6.255",
        "GDP_per _capita": "10.499",
        "SocialSupport": "0.935",
        "Healthy life expectancy": "67.906",
        "Freedom to make life choices": "0.773",
        "Generosity": "-0.203",
        "Perceptions of corruption": "0.826"
    },
    {
        "Country name": "Cyprus",
        "HappinessRank": "39",
        "HappinesScore": "6.223",
        "GDP_per _capita": "10.576",
        "SocialSupport": "0.802",
        "Healthy life expectancy": "73.898",
        "Freedom to make life choices": "0.763",
        "Generosity": "-0.015",
        "Perceptions of corruption": "0.844"
    },
    {
        "Country name": "Estonia",
        "HappinessRank": "40",
        "HappinesScore": "6.189",
        "GDP_per _capita": "10.481",
        "SocialSupport": "0.941",
        "Healthy life expectancy": "68.8",
        "Freedom to make life choices": "0.909",
        "Generosity": "-0.106",
        "Perceptions of corruption": "0.527"
    },
    {
        "Country name": "Panama",
        "HappinessRank": "41",
        "HappinesScore": "6.18",
        "GDP_per _capita": "10.35",
        "SocialSupport": "0.896",
        "Healthy life expectancy": "69.652",
        "Freedom to make life choices": "0.872",
        "Generosity": "-0.166",
        "Perceptions of corruption": "0.856"
    },
    {
        "Country name": "Uzbekistan",
        "HappinessRank": "42",
        "HappinesScore": "6.179",
        "GDP_per _capita": "8.836",
        "SocialSupport": "0.918",
        "Healthy life expectancy": "65.255",
        "Freedom to make life choices": "0.97",
        "Generosity": "0.311",
        "Perceptions of corruption": "0.515"
    },
    {
        "Country name": "Chile",
        "HappinessRank": "43",
        "HappinesScore": "6.172",
        "GDP_per _capita": "10.071",
        "SocialSupport": "0.882",
        "Healthy life expectancy": "70",
        "Freedom to make life choices": "0.742",
        "Generosity": "-0.044",
        "Perceptions of corruption": "0.83"
    },
    {
        "Country name": "Poland",
        "HappinessRank": "44",
        "HappinesScore": "6.166",
        "GDP_per _capita": "10.382",
        "SocialSupport": "0.898",
        "Healthy life expectancy": "69.702",
        "Freedom to make life choices": "0.841",
        "Generosity": "-0.165",
        "Perceptions of corruption": "0.735"
    },
    {
        "Country name": "Kazakhstan",
        "HappinessRank": "45",
        "HappinesScore": "6.152",
        "GDP_per _capita": "10.155",
        "SocialSupport": "0.952",
        "Healthy life expectancy": "65.2",
        "Freedom to make life choices": "0.853",
        "Generosity": "-0.069",
        "Perceptions of corruption": "0.733"
    },
    {
        "Country name": "Romania",
        "HappinessRank": "46",
        "HappinesScore": "6.14",
        "GDP_per _capita": "10.284",
        "SocialSupport": "0.832",
        "Healthy life expectancy": "67.355",
        "Freedom to make life choices": "0.845",
        "Generosity": "-0.219",
        "Perceptions of corruption": "0.938"
    },
    {
        "Country name": "Kuwait",
        "HappinessRank": "47",
        "HappinesScore": "6.106",
        "GDP_per _capita": "10.817",
        "SocialSupport": "0.843",
        "Healthy life expectancy": "66.9",
        "Freedom to make life choices": "0.867",
        "Generosity": "-0.104",
        "Perceptions of corruption": "0.736"
    },
    {
        "Country name": "Serbia",
        "HappinessRank": "48",
        "HappinesScore": "6.078",
        "GDP_per _capita": "9.787",
        "SocialSupport": "0.873",
        "Healthy life expectancy": "68.6",
        "Freedom to make life choices": "0.778",
        "Generosity": "0.002",
        "Perceptions of corruption": "0.835"
    },
    {
        "Country name": "El Salvador",
        "HappinessRank": "49",
        "HappinesScore": "6.061",
        "GDP_per _capita": "9.054",
        "SocialSupport": "0.762",
        "Healthy life expectancy": "66.402",
        "Freedom to make life choices": "0.888",
        "Generosity": "-0.11",
        "Perceptions of corruption": "0.688"
    },
    {
        "Country name": "Mauritius",
        "HappinessRank": "50",
        "HappinesScore": "6.049",
        "GDP_per _capita": "10.008",
        "SocialSupport": "0.905",
        "Healthy life expectancy": "66.701",
        "Freedom to make life choices": "0.867",
        "Generosity": "-0.054",
        "Perceptions of corruption": "0.789"
    },
    {
        "Country name": "Latvia",
        "HappinessRank": "51",
        "HappinesScore": "6.032",
        "GDP_per _capita": "10.315",
        "SocialSupport": "0.927",
        "Healthy life expectancy": "67.1",
        "Freedom to make life choices": "0.715",
        "Generosity": "-0.162",
        "Perceptions of corruption": "0.8"
    },
    {
        "Country name": "Colombia",
        "HappinessRank": "52",
        "HappinesScore": "6.012",
        "GDP_per _capita": "9.557",
        "SocialSupport": "0.847",
        "Healthy life expectancy": "68.001",
        "Freedom to make life choices": "0.837",
        "Generosity": "-0.135",
        "Perceptions of corruption": "0.841"
    },
    {
        "Country name": "Hungary",
        "HappinessRank": "53",
        "HappinesScore": "5.992",
        "GDP_per _capita": "10.358",
        "SocialSupport": "0.943",
        "Healthy life expectancy": "68",
        "Freedom to make life choices": "0.755",
        "Generosity": "-0.186",
        "Perceptions of corruption": "0.876"
    },
    {
        "Country name": "Thailand",
        "HappinessRank": "54",
        "HappinesScore": "5.985",
        "GDP_per _capita": "9.805",
        "SocialSupport": "0.888",
        "Healthy life expectancy": "67.401",
        "Freedom to make life choices": "0.884",
        "Generosity": "0.287",
        "Perceptions of corruption": "0.895"
    },
    {
        "Country name": "Nicaragua",
        "HappinessRank": "55",
        "HappinesScore": "5.972",
        "GDP_per _capita": "8.62",
        "SocialSupport": "0.864",
        "Healthy life expectancy": "67.657",
        "Freedom to make life choices": "0.836",
        "Generosity": "0.02",
        "Perceptions of corruption": "0.664"
    },
    {
        "Country name": "Japan",
        "HappinessRank": "56",
        "HappinesScore": "5.94",
        "GDP_per _capita": "10.611",
        "SocialSupport": "0.884",
        "Healthy life expectancy": "75.1",
        "Freedom to make life choices": "0.796",
        "Generosity": "-0.258",
        "Perceptions of corruption": "0.638"
    },
    {
        "Country name": "Argentina",
        "HappinessRank": "57",
        "HappinesScore": "5.929",
        "GDP_per _capita": "9.962",
        "SocialSupport": "0.898",
        "Healthy life expectancy": "69",
        "Freedom to make life choices": "0.828",
        "Generosity": "-0.182",
        "Perceptions of corruption": "0.834"
    },
    {
        "Country name": "Portugal",
        "HappinessRank": "58",
        "HappinesScore": "5.929",
        "GDP_per _capita": "10.421",
        "SocialSupport": "0.879",
        "Healthy life expectancy": "72.6",
        "Freedom to make life choices": "0.892",
        "Generosity": "-0.244",
        "Perceptions of corruption": "0.887"
    },
    {
        "Country name": "Honduras",
        "HappinessRank": "59",
        "HappinesScore": "5.919",
        "GDP_per _capita": "8.648",
        "SocialSupport": "0.812",
        "Healthy life expectancy": "67.3",
        "Freedom to make life choices": "0.857",
        "Generosity": "0.081",
        "Perceptions of corruption": "0.809"
    },
    {
        "Country name": "Croatia",
        "HappinessRank": "60",
        "HappinesScore": "5.882",
        "GDP_per _capita": "10.217",
        "SocialSupport": "0.924",
        "Healthy life expectancy": "70.799",
        "Freedom to make life choices": "0.754",
        "Generosity": "-0.118",
        "Perceptions of corruption": "0.939"
    },
    {
        "Country name": "Philippines",
        "HappinessRank": "61",
        "HappinesScore": "5.88",
        "GDP_per _capita": "9.076",
        "SocialSupport": "0.83",
        "Healthy life expectancy": "62",
        "Freedom to make life choices": "0.917",
        "Generosity": "-0.097",
        "Perceptions of corruption": "0.742"
    },
    {
        "Country name": "South Korea",
        "HappinessRank": "62",
        "HappinesScore": "5.845",
        "GDP_per _capita": "10.651",
        "SocialSupport": "0.799",
        "Healthy life expectancy": "73.9",
        "Freedom to make life choices": "0.672",
        "Generosity": "-0.083",
        "Perceptions of corruption": "0.727"
    },
    {
        "Country name": "Peru",
        "HappinessRank": "63",
        "HappinesScore": "5.84",
        "GDP_per _capita": "9.458",
        "SocialSupport": "0.832",
        "Healthy life expectancy": "68.25",
        "Freedom to make life choices": "0.822",
        "Generosity": "-0.154",
        "Perceptions of corruption": "0.891"
    },
    {
        "Country name": "Bosnia and Herzegovina",
        "HappinessRank": "64",
        "HappinesScore": "5.813",
        "GDP_per _capita": "9.59",
        "SocialSupport": "0.87",
        "Healthy life expectancy": "68.098",
        "Freedom to make life choices": "0.706",
        "Generosity": "0.113",
        "Perceptions of corruption": "0.931"
    },
    {
        "Country name": "Moldova",
        "HappinessRank": "65",
        "HappinesScore": "5.766",
        "GDP_per _capita": "9.454",
        "SocialSupport": "0.857",
        "Healthy life expectancy": "65.699",
        "Freedom to make life choices": "0.822",
        "Generosity": "-0.079",
        "Perceptions of corruption": "0.918"
    },
    {
        "Country name": "Ecuador",
        "HappinessRank": "66",
        "HappinesScore": "5.764",
        "GDP_per _capita": "9.313",
        "SocialSupport": "0.821",
        "Healthy life expectancy": "68.8",
        "Freedom to make life choices": "0.842",
        "Generosity": "-0.124",
        "Perceptions of corruption": "0.843"
    },
    {
        "Country name": "Kyrgyzstan",
        "HappinessRank": "67",
        "HappinesScore": "5.744",
        "GDP_per _capita": "8.538",
        "SocialSupport": "0.893",
        "Healthy life expectancy": "64.401",
        "Freedom to make life choices": "0.935",
        "Generosity": "0.119",
        "Perceptions of corruption": "0.908"
    },
    {
        "Country name": "Greece",
        "HappinessRank": "68",
        "HappinesScore": "5.723",
        "GDP_per _capita": "10.279",
        "SocialSupport": "0.823",
        "Healthy life expectancy": "72.6",
        "Freedom to make life choices": "0.582",
        "Generosity": "-0.288",
        "Perceptions of corruption": "0.823"
    },
    {
        "Country name": "Bolivia",
        "HappinessRank": "69",
        "HappinesScore": "5.716",
        "GDP_per _capita": "9.046",
        "SocialSupport": "0.81",
        "Healthy life expectancy": "63.901",
        "Freedom to make life choices": "0.875",
        "Generosity": "-0.077",
        "Perceptions of corruption": "0.839"
    },
    {
        "Country name": "Mongolia",
        "HappinessRank": "70",
        "HappinesScore": "5.677",
        "GDP_per _capita": "9.4",
        "SocialSupport": "0.935",
        "Healthy life expectancy": "62.5",
        "Freedom to make life choices": "0.708",
        "Generosity": "0.116",
        "Perceptions of corruption": "0.856"
    },
    {
        "Country name": "Paraguay",
        "HappinessRank": "71",
        "HappinesScore": "5.653",
        "GDP_per _capita": "9.448",
        "SocialSupport": "0.893",
        "Healthy life expectancy": "65.9",
        "Freedom to make life choices": "0.876",
        "Generosity": "0.028",
        "Perceptions of corruption": "0.882"
    },
    {
        "Country name": "Montenegro",
        "HappinessRank": "72",
        "HappinesScore": "5.581",
        "GDP_per _capita": "9.94",
        "SocialSupport": "0.858",
        "Healthy life expectancy": "68.699",
        "Freedom to make life choices": "0.708",
        "Generosity": "-0.034",
        "Perceptions of corruption": "0.812"
    },
    {
        "Country name": "Dominican Republic",
        "HappinessRank": "73",
        "HappinesScore": "5.545",
        "GDP_per _capita": "9.802",
        "SocialSupport": "0.853",
        "Healthy life expectancy": "66.102",
        "Freedom to make life choices": "0.86",
        "Generosity": "-0.133",
        "Perceptions of corruption": "0.714"
    },
    {
        "Country name": "North Cyprus",
        "HappinessRank": "74",
        "HappinesScore": "5.536",
        "GDP_per _capita": "10.576",
        "SocialSupport": "0.82",
        "Healthy life expectancy": "73.898",
        "Freedom to make life choices": "0.795",
        "Generosity": "0.012",
        "Perceptions of corruption": "0.626"
    },
    {
        "Country name": "Belarus",
        "HappinessRank": "75",
        "HappinesScore": "5.534",
        "GDP_per _capita": "9.853",
        "SocialSupport": "0.91",
        "Healthy life expectancy": "66.253",
        "Freedom to make life choices": "0.65",
        "Generosity": "-0.18",
        "Perceptions of corruption": "0.627"
    },
    {
        "Country name": "Russia",
        "HappinessRank": "76",
        "HappinesScore": "5.477",
        "GDP_per _capita": "10.189",
        "SocialSupport": "0.903",
        "Healthy life expectancy": "64.703",
        "Freedom to make life choices": "0.718",
        "Generosity": "-0.111",
        "Perceptions of corruption": "0.845"
    },
    {
        "Country name": "Hong Kong S.A.R. of China",
        "HappinessRank": "77",
        "HappinesScore": "5.477",
        "GDP_per _capita": "11",
        "SocialSupport": "0.836",
        "Healthy life expectancy": "76.82",
        "Freedom to make life choices": "0.717",
        "Generosity": "0.067",
        "Perceptions of corruption": "0.403"
    },
    {
        "Country name": "Tajikistan",
        "HappinessRank": "78",
        "HappinesScore": "5.466",
        "GDP_per _capita": "8.091",
        "SocialSupport": "0.86",
        "Healthy life expectancy": "64.281",
        "Freedom to make life choices": "0.832",
        "Generosity": "-0.056",
        "Perceptions of corruption": "0.553"
    },
    {
        "Country name": "Vietnam",
        "HappinessRank": "79",
        "HappinesScore": "5.411",
        "GDP_per _capita": "8.973",
        "SocialSupport": "0.85",
        "Healthy life expectancy": "68.034",
        "Freedom to make life choices": "0.94",
        "Generosity": "-0.098",
        "Perceptions of corruption": "0.796"
    },
    {
        "Country name": "Libya",
        "HappinessRank": "80",
        "HappinesScore": "5.41",
        "GDP_per _capita": "9.622",
        "SocialSupport": "0.827",
        "Healthy life expectancy": "62.3",
        "Freedom to make life choices": "0.771",
        "Generosity": "-0.087",
        "Perceptions of corruption": "0.667"
    },
    {
        "Country name": "Malaysia",
        "HappinessRank": "81",
        "HappinesScore": "5.384",
        "GDP_per _capita": "10.238",
        "SocialSupport": "0.817",
        "Healthy life expectancy": "67.102",
        "Freedom to make life choices": "0.895",
        "Generosity": "0.125",
        "Perceptions of corruption": "0.839"
    },
    {
        "Country name": "Indonesia",
        "HappinessRank": "82",
        "HappinesScore": "5.345",
        "GDP_per _capita": "9.365",
        "SocialSupport": "0.811",
        "Healthy life expectancy": "62.236",
        "Freedom to make life choices": "0.873",
        "Generosity": "0.542",
        "Perceptions of corruption": "0.867"
    },
    {
        "Country name": "Congo (Brazzaville)",
        "HappinessRank": "83",
        "HappinesScore": "5.342",
        "GDP_per _capita": "8.117",
        "SocialSupport": "0.636",
        "Healthy life expectancy": "58.221",
        "Freedom to make life choices": "0.695",
        "Generosity": "-0.068",
        "Perceptions of corruption": "0.745"
    },
    {
        "Country name": "China",
        "HappinessRank": "84",
        "HappinesScore": "5.339",
        "GDP_per _capita": "9.673",
        "SocialSupport": "0.811",
        "Healthy life expectancy": "69.593",
        "Freedom to make life choices": "0.904",
        "Generosity": "-0.146",
        "Perceptions of corruption": "0.755"
    },
    {
        "Country name": "Ivory Coast",
        "HappinessRank": "85",
        "HappinesScore": "5.306",
        "GDP_per _capita": "8.551",
        "SocialSupport": "0.644",
        "Healthy life expectancy": "50.114",
        "Freedom to make life choices": "0.741",
        "Generosity": "-0.016",
        "Perceptions of corruption": "0.794"
    },
    {
        "Country name": "Armenia",
        "HappinessRank": "86",
        "HappinesScore": "5.283",
        "GDP_per _capita": "9.487",
        "SocialSupport": "0.799",
        "Healthy life expectancy": "67.055",
        "Freedom to make life choices": "0.825",
        "Generosity": "-0.168",
        "Perceptions of corruption": "0.629"
    },
    {
        "Country name": "Nepal",
        "HappinessRank": "87",
        "HappinesScore": "5.269",
        "GDP_per _capita": "8.12",
        "SocialSupport": "0.774",
        "Healthy life expectancy": "64.233",
        "Freedom to make life choices": "0.782",
        "Generosity": "0.152",
        "Perceptions of corruption": "0.727"
    },
    {
        "Country name": "Bulgaria",
        "HappinessRank": "88",
        "HappinesScore": "5.266",
        "GDP_per _capita": "10.016",
        "SocialSupport": "0.931",
        "Healthy life expectancy": "67",
        "Freedom to make life choices": "0.788",
        "Generosity": "-0.096",
        "Perceptions of corruption": "0.932"
    },
    {
        "Country name": "Maldives",
        "HappinessRank": "89",
        "HappinesScore": "5.198",
        "GDP_per _capita": "9.826",
        "SocialSupport": "0.913",
        "Healthy life expectancy": "70.6",
        "Freedom to make life choices": "0.854",
        "Generosity": "0.024",
        "Perceptions of corruption": "0.825"
    },
    {
        "Country name": "Azerbaijan",
        "HappinessRank": "90",
        "HappinesScore": "5.171",
        "GDP_per _capita": "9.569",
        "SocialSupport": "0.836",
        "Healthy life expectancy": "65.656",
        "Freedom to make life choices": "0.814",
        "Generosity": "-0.223",
        "Perceptions of corruption": "0.506"
    },
    {
        "Country name": "Cameroon",
        "HappinessRank": "91",
        "HappinesScore": "5.142",
        "GDP_per _capita": "8.189",
        "SocialSupport": "0.71",
        "Healthy life expectancy": "53.515",
        "Freedom to make life choices": "0.731",
        "Generosity": "0.026",
        "Perceptions of corruption": "0.848"
    },
    {
        "Country name": "Senegal",
        "HappinessRank": "92",
        "HappinesScore": "5.132",
        "GDP_per _capita": "8.118",
        "SocialSupport": "0.71",
        "Healthy life expectancy": "59.802",
        "Freedom to make life choices": "0.695",
        "Generosity": "-0.046",
        "Perceptions of corruption": "0.801"
    },
    {
        "Country name": "Albania",
        "HappinessRank": "93",
        "HappinesScore": "5.117",
        "GDP_per _capita": "9.52",
        "SocialSupport": "0.697",
        "Healthy life expectancy": "68.999",
        "Freedom to make life choices": "0.785",
        "Generosity": "-0.03",
        "Perceptions of corruption": "0.901"
    },
    {
        "Country name": "North Macedonia",
        "HappinessRank": "94",
        "HappinesScore": "5.101",
        "GDP_per _capita": "9.693",
        "SocialSupport": "0.805",
        "Healthy life expectancy": "65.474",
        "Freedom to make life choices": "0.751",
        "Generosity": "0.038",
        "Perceptions of corruption": "0.905"
    },
    {
        "Country name": "Ghana",
        "HappinessRank": "95",
        "HappinesScore": "5.088",
        "GDP_per _capita": "8.58",
        "SocialSupport": "0.727",
        "Healthy life expectancy": "57.586",
        "Freedom to make life choices": "0.807",
        "Generosity": "0.123",
        "Perceptions of corruption": "0.848"
    },
    {
        "Country name": "Niger",
        "HappinessRank": "96",
        "HappinesScore": "5.074",
        "GDP_per _capita": "7.098",
        "SocialSupport": "0.641",
        "Healthy life expectancy": "53.78",
        "Freedom to make life choices": "0.806",
        "Generosity": "0.018",
        "Perceptions of corruption": "0.693"
    },
    {
        "Country name": "Turkmenistan",
        "HappinessRank": "97",
        "HappinesScore": "5.066",
        "GDP_per _capita": "9.629",
        "SocialSupport": "0.983",
        "Healthy life expectancy": "62.409",
        "Freedom to make life choices": "0.877",
        "Generosity": "0.273",
        "Perceptions of corruption": "0.888"
    },
    {
        "Country name": "Gambia",
        "HappinessRank": "98",
        "HappinesScore": "5.051",
        "GDP_per _capita": "7.686",
        "SocialSupport": "0.69",
        "Healthy life expectancy": "55.16",
        "Freedom to make life choices": "0.697",
        "Generosity": "0.424",
        "Perceptions of corruption": "0.746"
    },
    {
        "Country name": "Benin",
        "HappinessRank": "99",
        "HappinesScore": "5.045",
        "GDP_per _capita": "8.087",
        "SocialSupport": "0.489",
        "Healthy life expectancy": "54.713",
        "Freedom to make life choices": "0.757",
        "Generosity": "-0.034",
        "Perceptions of corruption": "0.661"
    },
    {
        "Country name": "Laos",
        "HappinessRank": "100",
        "HappinesScore": "5.03",
        "GDP_per _capita": "8.947",
        "SocialSupport": "0.728",
        "Healthy life expectancy": "58.968",
        "Freedom to make life choices": "0.91",
        "Generosity": "0.123",
        "Perceptions of corruption": "0.658"
    },
    {
        "Country name": "Bangladesh",
        "HappinessRank": "101",
        "HappinesScore": "5.025",
        "GDP_per _capita": "8.454",
        "SocialSupport": "0.693",
        "Healthy life expectancy": "64.8",
        "Freedom to make life choices": "0.877",
        "Generosity": "-0.041",
        "Perceptions of corruption": "0.682"
    },
    {
        "Country name": "Guinea",
        "HappinessRank": "102",
        "HappinesScore": "4.984",
        "GDP_per _capita": "7.838",
        "SocialSupport": "0.639",
        "Healthy life expectancy": "55.008",
        "Freedom to make life choices": "0.697",
        "Generosity": "0.095",
        "Perceptions of corruption": "0.766"
    },
    {
        "Country name": "South Africa",
        "HappinessRank": "103",
        "HappinesScore": "4.956",
        "GDP_per _capita": "9.403",
        "SocialSupport": "0.86",
        "Healthy life expectancy": "56.904",
        "Freedom to make life choices": "0.749",
        "Generosity": "-0.067",
        "Perceptions of corruption": "0.86"
    },
    {
        "Country name": "Turkey",
        "HappinessRank": "104",
        "HappinesScore": "4.948",
        "GDP_per _capita": "10.24",
        "SocialSupport": "0.822",
        "Healthy life expectancy": "67.199",
        "Freedom to make life choices": "0.576",
        "Generosity": "-0.139",
        "Perceptions of corruption": "0.776"
    },
    {
        "Country name": "Pakistan",
        "HappinessRank": "105",
        "HappinesScore": "4.934",
        "GDP_per _capita": "8.458",
        "SocialSupport": "0.651",
        "Healthy life expectancy": "58.709",
        "Freedom to make life choices": "0.726",
        "Generosity": "0.098",
        "Perceptions of corruption": "0.787"
    },
    {
        "Country name": "Morocco",
        "HappinessRank": "106",
        "HappinesScore": "4.918",
        "GDP_per _capita": "8.903",
        "SocialSupport": "0.56",
        "Healthy life expectancy": "66.208",
        "Freedom to make life choices": "0.774",
        "Generosity": "-0.236",
        "Perceptions of corruption": "0.801"
    },
    {
        "Country name": "Venezuela",
        "HappinessRank": "107",
        "HappinesScore": "4.892",
        "GDP_per _capita": "9.073",
        "SocialSupport": "0.861",
        "Healthy life expectancy": "66.7",
        "Freedom to make life choices": "0.615",
        "Generosity": "-0.169",
        "Perceptions of corruption": "0.827"
    },
    {
        "Country name": "Georgia",
        "HappinessRank": "108",
        "HappinesScore": "4.891",
        "GDP_per _capita": "9.585",
        "SocialSupport": "0.671",
        "Healthy life expectancy": "64.3",
        "Freedom to make life choices": "0.783",
        "Generosity": "-0.238",
        "Perceptions of corruption": "0.655"
    },
    {
        "Country name": "Algeria",
        "HappinessRank": "109",
        "HappinesScore": "4.887",
        "GDP_per _capita": "9.342",
        "SocialSupport": "0.802",
        "Healthy life expectancy": "66.005",
        "Freedom to make life choices": "0.48",
        "Generosity": "-0.067",
        "Perceptions of corruption": "0.752"
    },
    {
        "Country name": "Ukraine",
        "HappinessRank": "110",
        "HappinesScore": "4.875",
        "GDP_per _capita": "9.436",
        "SocialSupport": "0.888",
        "Healthy life expectancy": "64.902",
        "Freedom to make life choices": "0.724",
        "Generosity": "-0.011",
        "Perceptions of corruption": "0.924"
    },
    {
        "Country name": "Iraq",
        "HappinessRank": "111",
        "HappinesScore": "4.854",
        "GDP_per _capita": "9.24",
        "SocialSupport": "0.746",
        "Healthy life expectancy": "60.583",
        "Freedom to make life choices": "0.63",
        "Generosity": "-0.053",
        "Perceptions of corruption": "0.875"
    },
    {
        "Country name": "Gabon",
        "HappinessRank": "112",
        "HappinesScore": "4.852",
        "GDP_per _capita": "9.603",
        "SocialSupport": "0.776",
        "Healthy life expectancy": "59.962",
        "Freedom to make life choices": "0.731",
        "Generosity": "-0.2",
        "Perceptions of corruption": "0.84"
    },
    {
        "Country name": "Burkina Faso",
        "HappinessRank": "113",
        "HappinesScore": "4.834",
        "GDP_per _capita": "7.678",
        "SocialSupport": "0.672",
        "Healthy life expectancy": "54.151",
        "Freedom to make life choices": "0.695",
        "Generosity": "-0.009",
        "Perceptions of corruption": "0.748"
    },
    {
        "Country name": "Cambodia",
        "HappinessRank": "114",
        "HappinesScore": "4.83",
        "GDP_per _capita": "8.36",
        "SocialSupport": "0.765",
        "Healthy life expectancy": "62",
        "Freedom to make life choices": "0.959",
        "Generosity": "0.034",
        "Perceptions of corruption": "0.843"
    },
    {
        "Country name": "Mozambique",
        "HappinessRank": "115",
        "HappinesScore": "4.794",
        "GDP_per _capita": "7.158",
        "SocialSupport": "0.744",
        "Healthy life expectancy": "54.706",
        "Freedom to make life choices": "0.882",
        "Generosity": "0.061",
        "Perceptions of corruption": "0.684"
    },
    {
        "Country name": "Nigeria",
        "HappinessRank": "116",
        "HappinesScore": "4.759",
        "GDP_per _capita": "8.533",
        "SocialSupport": "0.74",
        "Healthy life expectancy": "50.102",
        "Freedom to make life choices": "0.737",
        "Generosity": "0.037",
        "Perceptions of corruption": "0.878"
    },
    {
        "Country name": "Mali",
        "HappinessRank": "117",
        "HappinesScore": "4.723",
        "GDP_per _capita": "7.744",
        "SocialSupport": "0.724",
        "Healthy life expectancy": "51.969",
        "Freedom to make life choices": "0.697",
        "Generosity": "-0.036",
        "Perceptions of corruption": "0.827"
    },
    {
        "Country name": "Iran",
        "HappinessRank": "118",
        "HappinesScore": "4.721",
        "GDP_per _capita": "9.584",
        "SocialSupport": "0.71",
        "Healthy life expectancy": "66.3",
        "Freedom to make life choices": "0.608",
        "Generosity": "0.218",
        "Perceptions of corruption": "0.714"
    },
    {
        "Country name": "Uganda",
        "HappinessRank": "119",
        "HappinesScore": "4.636",
        "GDP_per _capita": "7.677",
        "SocialSupport": "0.781",
        "Healthy life expectancy": "56.101",
        "Freedom to make life choices": "0.709",
        "Generosity": "0.122",
        "Perceptions of corruption": "0.855"
    },
    {
        "Country name": "Liberia",
        "HappinessRank": "120",
        "HappinesScore": "4.625",
        "GDP_per _capita": "7.288",
        "SocialSupport": "0.72",
        "Healthy life expectancy": "56.498",
        "Freedom to make life choices": "0.735",
        "Generosity": "0.05",
        "Perceptions of corruption": "0.85"
    },
    {
        "Country name": "Kenya",
        "HappinessRank": "121",
        "HappinesScore": "4.607",
        "GDP_per _capita": "8.361",
        "SocialSupport": "0.688",
        "Healthy life expectancy": "60.704",
        "Freedom to make life choices": "0.779",
        "Generosity": "0.287",
        "Perceptions of corruption": "0.825"
    },
    {
        "Country name": "Tunisia",
        "HappinessRank": "122",
        "HappinesScore": "4.596",
        "GDP_per _capita": "9.266",
        "SocialSupport": "0.691",
        "Healthy life expectancy": "67.201",
        "Freedom to make life choices": "0.656",
        "Generosity": "-0.201",
        "Perceptions of corruption": "0.87"
    },
    {
        "Country name": "Lebanon",
        "HappinessRank": "123",
        "HappinesScore": "4.584",
        "GDP_per _capita": "9.626",
        "SocialSupport": "0.848",
        "Healthy life expectancy": "67.355",
        "Freedom to make life choices": "0.525",
        "Generosity": "-0.073",
        "Perceptions of corruption": "0.898"
    },
    {
        "Country name": "Namibia",
        "HappinessRank": "124",
        "HappinesScore": "4.574",
        "GDP_per _capita": "9.161",
        "SocialSupport": "0.818",
        "Healthy life expectancy": "56.799",
        "Freedom to make life choices": "0.719",
        "Generosity": "-0.149",
        "Perceptions of corruption": "0.847"
    },
    {
        "Country name": "Palestinian Territories",
        "HappinessRank": "125",
        "HappinesScore": "4.517",
        "GDP_per _capita": "8.485",
        "SocialSupport": "0.826",
        "Healthy life expectancy": "62.25",
        "Freedom to make life choices": "0.653",
        "Generosity": "-0.163",
        "Perceptions of corruption": "0.821"
    },
    {
        "Country name": "Myanmar",
        "HappinessRank": "126",
        "HappinesScore": "4.426",
        "GDP_per _capita": "8.541",
        "SocialSupport": "0.779",
        "Healthy life expectancy": "59.302",
        "Freedom to make life choices": "0.876",
        "Generosity": "0.509",
        "Perceptions of corruption": "0.66"
    },
    {
        "Country name": "Jordan",
        "HappinessRank": "127",
        "HappinesScore": "4.395",
        "GDP_per _capita": "9.182",
        "SocialSupport": "0.767",
        "Healthy life expectancy": "67",
        "Freedom to make life choices": "0.755",
        "Generosity": "-0.167",
        "Perceptions of corruption": "0.705"
    },
    {
        "Country name": "Chad",
        "HappinessRank": "128",
        "HappinesScore": "4.355",
        "GDP_per _capita": "7.364",
        "SocialSupport": "0.619",
        "Healthy life expectancy": "48.478",
        "Freedom to make life choices": "0.579",
        "Generosity": "0.041",
        "Perceptions of corruption": "0.807"
    },
    {
        "Country name": "Sri Lanka",
        "HappinessRank": "129",
        "HappinesScore": "4.325",
        "GDP_per _capita": "9.47",
        "SocialSupport": "0.827",
        "Healthy life expectancy": "67.299",
        "Freedom to make life choices": "0.841",
        "Generosity": "0.079",
        "Perceptions of corruption": "0.863"
    },
    {
        "Country name": "Swaziland",
        "HappinessRank": "130",
        "HappinesScore": "4.308",
        "GDP_per _capita": "9.065",
        "SocialSupport": "0.77",
        "Healthy life expectancy": "50.833",
        "Freedom to make life choices": "0.647",
        "Generosity": "-0.185",
        "Perceptions of corruption": "0.708"
    },
    {
        "Country name": "Comoros",
        "HappinessRank": "131",
        "HappinesScore": "4.289",
        "GDP_per _capita": "8.031",
        "SocialSupport": "0.626",
        "Healthy life expectancy": "57.349",
        "Freedom to make life choices": "0.548",
        "Generosity": "0.082",
        "Perceptions of corruption": "0.781"
    },
    {
        "Country name": "Egypt",
        "HappinessRank": "132",
        "HappinesScore": "4.283",
        "GDP_per _capita": "9.367",
        "SocialSupport": "0.75",
        "Healthy life expectancy": "61.998",
        "Freedom to make life choices": "0.749",
        "Generosity": "-0.182",
        "Perceptions of corruption": "0.795"
    },
    {
        "Country name": "Ethiopia",
        "HappinessRank": "133",
        "HappinesScore": "4.275",
        "GDP_per _capita": "7.694",
        "SocialSupport": "0.764",
        "Healthy life expectancy": "59",
        "Freedom to make life choices": "0.752",
        "Generosity": "0.082",
        "Perceptions of corruption": "0.761"
    },
    {
        "Country name": "Mauritania",
        "HappinessRank": "134",
        "HappinesScore": "4.227",
        "GDP_per _capita": "8.542",
        "SocialSupport": "0.795",
        "Healthy life expectancy": "57.161",
        "Freedom to make life choices": "0.561",
        "Generosity": "-0.106",
        "Perceptions of corruption": "0.731"
    },
    {
        "Country name": "Madagascar",
        "HappinessRank": "135",
        "HappinesScore": "4.208",
        "GDP_per _capita": "7.396",
        "SocialSupport": "0.686",
        "Healthy life expectancy": "59.305",
        "Freedom to make life choices": "0.552",
        "Generosity": "-0.005",
        "Perceptions of corruption": "0.803"
    },
    {
        "Country name": "Togo",
        "HappinessRank": "136",
        "HappinesScore": "4.107",
        "GDP_per _capita": "7.362",
        "SocialSupport": "0.569",
        "Healthy life expectancy": "54.914",
        "Freedom to make life choices": "0.619",
        "Generosity": "0.032",
        "Perceptions of corruption": "0.772"
    },
    {
        "Country name": "Zambia",
        "HappinessRank": "137",
        "HappinesScore": "4.073",
        "GDP_per _capita": "8.145",
        "SocialSupport": "0.708",
        "Healthy life expectancy": "55.809",
        "Freedom to make life choices": "0.782",
        "Generosity": "0.061",
        "Perceptions of corruption": "0.823"
    },
    {
        "Country name": "Sierra Leone",
        "HappinessRank": "138",
        "HappinesScore": "3.849",
        "GDP_per _capita": "7.434",
        "SocialSupport": "0.63",
        "Healthy life expectancy": "51.651",
        "Freedom to make life choices": "0.717",
        "Generosity": "0.084",
        "Perceptions of corruption": "0.866"
    },
    {
        "Country name": "India",
        "HappinessRank": "139",
        "HappinesScore": "3.819",
        "GDP_per _capita": "8.755",
        "SocialSupport": "0.603",
        "Healthy life expectancy": "60.633",
        "Freedom to make life choices": "0.893",
        "Generosity": "0.089",
        "Perceptions of corruption": "0.774"
    },
    {
        "Country name": "Burundi",
        "HappinessRank": "140",
        "HappinesScore": "3.775",
        "GDP_per _capita": "6.635",
        "SocialSupport": "0.49",
        "Healthy life expectancy": "53.4",
        "Freedom to make life choices": "0.626",
        "Generosity": "-0.024",
        "Perceptions of corruption": "0.607"
    },
    {
        "Country name": "Yemen",
        "HappinessRank": "141",
        "HappinesScore": "3.658",
        "GDP_per _capita": "7.578",
        "SocialSupport": "0.832",
        "Healthy life expectancy": "57.122",
        "Freedom to make life choices": "0.602",
        "Generosity": "-0.147",
        "Perceptions of corruption": "0.8"
    },
    {
        "Country name": "Tanzania",
        "HappinessRank": "142",
        "HappinesScore": "3.623",
        "GDP_per _capita": "7.876",
        "SocialSupport": "0.702",
        "Healthy life expectancy": "57.999",
        "Freedom to make life choices": "0.833",
        "Generosity": "0.183",
        "Perceptions of corruption": "0.577"
    },
    {
        "Country name": "Haiti",
        "HappinessRank": "143",
        "HappinesScore": "3.615",
        "GDP_per _capita": "7.477",
        "SocialSupport": "0.54",
        "Healthy life expectancy": "55.7",
        "Freedom to make life choices": "0.593",
        "Generosity": "0.422",
        "Perceptions of corruption": "0.721"
    },
    {
        "Country name": "Malawi",
        "HappinessRank": "144",
        "HappinesScore": "3.6",
        "GDP_per _capita": "6.958",
        "SocialSupport": "0.537",
        "Healthy life expectancy": "57.948",
        "Freedom to make life choices": "0.78",
        "Generosity": "0.038",
        "Perceptions of corruption": "0.729"
    },
    {
        "Country name": "Lesotho",
        "HappinessRank": "145",
        "HappinesScore": "3.512",
        "GDP_per _capita": "7.926",
        "SocialSupport": "0.787",
        "Healthy life expectancy": "48.7",
        "Freedom to make life choices": "0.715",
        "Generosity": "-0.131",
        "Perceptions of corruption": "0.915"
    },
    {
        "Country name": "Botswana",
        "HappinessRank": "146",
        "HappinesScore": "3.467",
        "GDP_per _capita": "9.782",
        "SocialSupport": "0.784",
        "Healthy life expectancy": "59.269",
        "Freedom to make life choices": "0.824",
        "Generosity": "-0.246",
        "Perceptions of corruption": "0.801"
    },
    {
        "Country name": "Rwanda",
        "HappinessRank": "147",
        "HappinesScore": "3.415",
        "GDP_per _capita": "7.676",
        "SocialSupport": "0.552",
        "Healthy life expectancy": "61.4",
        "Freedom to make life choices": "0.897",
        "Generosity": "0.061",
        "Perceptions of corruption": "0.167"
    },
    {
        "Country name": "Zimbabwe",
        "HappinessRank": "148",
        "HappinesScore": "3.145",
        "GDP_per _capita": "7.943",
        "SocialSupport": "0.75",
        "Healthy life expectancy": "56.201",
        "Freedom to make life choices": "0.677",
        "Generosity": "-0.047",
        "Perceptions of corruption": "0.821"
    },
    {
        "Country name": "Afghanistan",
        "HappinessRank": "149",
        "HappinesScore": "2.523",
        "GDP_per _capita": "7.695",
        "SocialSupport": "0.463",
        "Healthy life expectancy": "52.493",
        "Freedom to make life choices": "0.382",
        "Generosity": "-0.102",
        "Perceptions of corruption": "0.924"
    }
]