{
    "country_names":[
        "Finland",
    "Denmark",
    "Norway",
    "Iceland",
    "Netherlands",
    "Switzerland",
    "Sweden",
    "New Zealand",
    "Canada",
    "Austria",
    "Australia",
    "Costa Rica",
    "Israel",
    "Luxembourg",
    "United Kingdom",
    "Ireland",
    "Germany",
    "Belgium",
    "United States",
    "Czech Republic",
    "United Arab Emirates",
    "Malta",
    "Mexico",
    "France",
    "Taiwan",
    "Chile",
    "Guatemala",
    "Saudi Arabia",
    "Qatar",
    "Spain",
    "Panama",
    "Brazil",
    "Uruguay",
    "Singapore",
    "El Salvador",
    "Italy",
    "Bahrain",
    "Slovakia",
    "Trinidad & Tobago",
    "Poland",
    "Uzbekistan",
    "Lithuania",
    "Colombia",
    "Slovenia",
    "Nicaragua",
    "Kosovo",
    "Argentina",
    "Romania",
    "Cyprus",
    "Ecuador",
    "Kuwait",
    "Thailand",
    "Latvia",
    "South Korea",
    "Estonia",
    "Jamaica",
    "Mauritius",
    "Japan",
    "Honduras",
    "Kazakhstan",
    "Bolivia",
    "Hungary",
    "Paraguay",
    "Northern Cyprus",
    "Peru",
    "Portugal",
    "Pakistan",
    "Russia",
    "Philippines",
    "Serbia",
    "Moldova",
    "Libya",
    "Montenegro",
    "Tajikistan",
    "Croatia",
    "Hong Kong",
    "Dominican Republic",
    "Bosnia and Herzegovina",
    "Turkey",
    "Malaysia",
    "Belarus",
    "Greece",
    "Mongolia",
    "North Macedonia",
    "Nigeria",
    "Kyrgyzstan",
    "Turkmenistan",
    "Algeria",
    "Morocco",
    "Azerbaijan",
    "Lebanon",
    "Indonesia",
    "China",
    "Vietnam",
    "Bhutan",
    "Cameroon",
    "Bulgaria",
    "Ghana",
    "Ivory Coast",
    "Nepal",
    "Jordan",
    "Benin",
    "Congo (Brazzaville)",
    "Gabon",
    "Laos",
    "South Africa",
    "Albania",
    "Venezuela",
    "Cambodia",
    "Palestinian Territories",
    "Senegal",
    "Somalia",
    "Namibia",
    "Niger",
    "Burkina Faso",
    "Armenia",
    "Iran",
    "Guinea",
    "Georgia",
    "Gambia",
    "Kenya",
    "Mauritania",
    "Mozambique",
    "Tunisia",
    "Bangladesh",
    "Iraq",
    "Congo (Kinshasa)",
    "Mali",
    "Sierra Leone",
    "Sri Lanka",
    "Myanmar",
    "Chad",
    "Ukraine",
    "Ethiopia",
    "Swaziland",
    "Uganda",
    "Egypt",
    "Zambia",
    "Togo",
    "India",
    "Liberia",
    "Comoros",
    "Madagascar",
    "Lesotho",
    "Burundi",
    "Zimbabwe",
    "Haiti",
    "Botswana",
    "Syria",
    "Malawi",
    "Yemen",
    "Rwanda",
    "Tanzania",
    "Afghanistan",
    "Central African Republic",
    "South Sudan"
    ],
    "metadata": [
    {
        "countries": "Finland",
        "HappinessRank": 1,
        "HappinessScore": 7.77,
        "GDP_per_capita": 1.34,
        "SocialSupport": 1.59,
        "Healthy life expectancy": 0.99,
        "Freedom to make life choices": 0.60,
        "Generosity": 0.15,
        "Perceptions of corruption": 0.39
    },
    {
        "countries": "Denmark",
        "HappinessRank": 2,
        "HappinessScore": 7.60,
        "GDP_per_capita": 1.38,
        "SocialSupport": 1.57,
        "Healthy life expectancy": 1.00,
        "Freedom to make life choices": 0.59,
        "Generosity": 0.25,
        "Perceptions of corruption": 0.41
    },
    {
        "countries": "Norway",
        "HappinessRank": 3, 
        "HappinessScore": 7.55,
        "GDP_per_capita": 1.49,
        "SocialSupport": 1.58,
        "Healthy life expectancy": 1.03,
        "Freedom to make life choices": 0.60,
        "Generosity": 0.27,
        "Perceptions of corruption": 0.34
    },
    {
        "countries": "Iceland",
        "HappinessRank": 4,
        "HappinessScore": 7.49,
        "GDP_per_capita": 1.38,
        "SocialSupport": 1.62,
        "Healthy life expectancy": 1.03,
        "Freedom to make life choices":0.59,
        "Generosity": 0.35,
        "Perceptions of corruption": 0.12
    },
    {
        "countries": "Netherlands",
        "HappinessRank": 5,
        "HappinessScore": 7.49,
        "GDP_per_capita": 1.40,
        "SocialSupport": 1.52,
        "Healthy life expectancy": 1.00,
        "Freedom to make life choices": 0.56,
        "Generosity": 0.32,
        "Perceptions of corruption": 0.30
    },
    {
        "countries": "Switzerland",
        "HappinessRank": 6,
        "HappinessScore": 7.48,
        "GDP_per_capita": 1.45,
        "SocialSupport": 1.53,
        "Healthy life expectancy": 1.05,
        "Freedom to make life choices": 0.57,
        "Generosity": 0.26,
        "Perceptions of corruption": 0.34
    },
    {
        "countries": "Sweden",
        "HappinessRank": 7,
        "HappinessScore": 7.34,
        "GDP_per_capita": 1.39,
        "SocialSupport": 1.49,
        "Healthy life expectancy": 1.01,
        "Freedom to make life choices": 0.57,
        "Generosity": 0.27,
        "Perceptions of corruption": 0.37
    },
    {
        "countries": "New Zealand",
        "HappinessRank": 8,
        "HappinessScore": 7.31,
        "GDP_per_capita": 1.30,
        "SocialSupport": 1.56,
        "Healthy life expectancy": 1.03,
        "Freedom to make life choices": 0.59,
        "Generosity": 0.33,
        "Perceptions of corruption": 0.38
    },
    {
        "countries": "Canada",
        "HappinessRank": 9,
        "HappinessScore": 7.28,
        "GDP_per_capita": 1.37,
        "SocialSupport": 1.51,
        "Healthy life expectancy": 1.04,
        "Freedom to make life choices": 0.58,
        "Generosity": 0.29,
        "Perceptions of corruption": 0.31
    },
    {
        "countries": "Austria",
        "HappinessRank": 10,
        "HappinessScore": 7.25,
        "GDP_per_capita": 1.38,
        "SocialSupport": 1.48,
        "Healthy life expectancy": 1.02,
        "Freedom to make life choices": 0.53,
        "Generosity": 0.24,
        "Perceptions of corruption": 0.23
    },
    {
        "countries": "Australia",
        "HappinessRank": 11,
        "HappinessScore": 7.23,
        "GDP_per_capita": 1.37,
        "SocialSupport": 1.55,
        "Healthy life expectancy": 1.04,
        "Freedom to make life choices": 0.56,
        "Generosity": 0.33,
        "Perceptions of corruption": 0.29
    },
    {
        "countries": "Costa Rica",
        "HappinessRank": 12,
        "HappinessScore": 7.17,
        "GDP_per_capita": 1.03,
        "SocialSupport": 1.44,
        "Healthy life expectancy": 0.96,
        "Freedom to make life choices": 0.56,
        "Generosity": 0.14,
        "Perceptions of corruption": 0.09
    },
    {
        "countries": "Israel",
        "HappinessRank": 13,
        "HappinessScore":7.14,
        "GDP_per_capita": 1.28,
        "SocialSupport": 1.46,
        "Healthy life expectancy": 1.03,
        "Freedom to make life choices": 0.37,
        "Generosity": 0.26,
        "Perceptions of corruption": 0.08
    },
    {
        "countries": "Luxembourg",
        "HappinessRank": 14,
        "HappinessScore": 7.09,
        "GDP_per_capita": 1.61,
        "SocialSupport": 1.48,
        "Healthy life expectancy": 1.01,
        "Freedom to make life choices": 0.53,
        "Generosity": 0.19,
        "Perceptions of corruption": 0.32
    },
    {
        "countries": "United Kingdom",
        "HappinessRank": 15,
        "HappinessScore": 7.05,
        "GDP_per_capita": 1.33,
        "SocialSupport": 1.54,
        "Healthy life expectancy": 1.00,
        "Freedom to make life choices": 0.45,
        "Generosity": 0.35,
        "Perceptions of corruption": 0.28
    },
    {
        "countries": "Ireland",
        "HappinessRank": 16,
        "HappinessScore": 7.02,
        "GDP_per_capita": 1.50,
        "SocialSupport": 1.55,
        "Healthy life expectancy": 1.00,
        "Freedom to make life choices": 0.52,
        "Generosity": 0.30,
        "Perceptions of corruption": 0.31
    },
    {
        "countries": "Germany",
        "HappinessRank": 17,
        "HappinessScore": 6.99,
        "GDP_per_capita": 1.37,
        "SocialSupport": 1.45,
        "Healthy life expectancy": 0.99,
        "Freedom to make life choices": 0.50,
        "Generosity": 0.26,
        "Perceptions of corruption": 0.27
    },
    {
        "countries": "Belgium",
        "HappinessRank": 18,
        "HappinessScore": 6.92,
        "GDP_per_capita": 1.36,
        "SocialSupport": 1.50,
        "Healthy life expectancy": 0.99,
        "Freedom to make life choices": 0.47,
        "Generosity": 0.16,
        "Perceptions of corruption": 0.21
    },
    {
        "countries": "United States",
        "HappinessRank": 19,
        "HappinessScore": 6.89,
        "GDP_per_capita": 1.43,
        "SocialSupport": 1.46,
        "Healthy life expectancy": 0.87,
        "Freedom to make life choices": 0.45,
        "Generosity": 0.28,
        "Perceptions of corruption": 0.13
    },
    {
        "countries": "Czech Republic",
        "HappinessRank": 20,
        "HappinessScore": 6.85,
        "GDP_per_capita": 1.27,
        "SocialSupport": 1.49,
        "Healthy life expectancy": 0.92,
        "Freedom to make life choices": 0.46,
        "Generosity": 0.05,
        "Perceptions of corruption": 0.04
    },
    {
        "countries": "United Arab Emirates",
        "HappinessRank": 21,
        "HappinessScore": 6.83,
        "GDP_per_capita": 1.50,
        "SocialSupport": 1.31,
        "Healthy life expectancy": 0.83,
        "Freedom to make life choices": 0.60,
        "Generosity": 0.26,
        "Perceptions of corruption": 0.18
    },
    {
        "countries": "Malta",
        "HappinessRank": 22,
        "HappinessScore": 6.73,
        "GDP_per_capita": 1.30,
        "SocialSupport": 1.52,
        "Healthy life expectancy": 1.00,
        "Freedom to make life choices": 0.56,
        "Generosity": 0.38,
        "Perceptions of corruption": 0.15
    },
    {
        "countries": "Mexico",
        "HappinessRank": 23,
        "HappinessScore": 6.60,
        "GDP_per_capita": 1.07,
        "SocialSupport": 1.32,
        "Healthy life expectancy": 0.86,
        "Freedom to make life choices": 0.43,
        "Generosity": 0.07,
        "Perceptions of corruption": 0.07
    },
    {
        "countries": "France",
        "HappinessRank": 24,
        "HappinessScore": 6.59,
        "GDP_per_capita": 1.32,
        "SocialSupport": 1.47,
        "Healthy life expectancy": 1.05,
        "Freedom to make life choices": 0.44,
        "Generosity": 0.11,
        "Perceptions of corruption": 0.18
    },
    {
        "countries": "Taiwan",
        "HappinessRank": 25,
        "HappinessScore": 6.45,
        "GDP_per_capita": 1.37,
        "SocialSupport": 1.43,
        "Healthy life expectancy": 0.91,
        "Freedom to make life choices": 0.35,
        "Generosity": 0.24,
        "Perceptions of corruption": 0.10
    },
    {
        "countries": "Chile",
        "HappinessRank": 26,
        "HappinessScore": 6.44,
        "GDP_per_capita": 1.16,
        "SocialSupport": 1.37,
        "Healthy life expectancy": 0.92,
        "Freedom to make life choices": 0.36,
        "Generosity": 0.19,
        "Perceptions of corruption": 0.06
    },
    {
        "countries": "Guatemala",
        "HappinessRank": 27,
        "HappinessScore": 6.44,
        "GDP_per_capita": 0.80,
        "SocialSupport": 1.27,
        "Healthy life expectancy": 0.75,
        "Freedom to make life choices": 0.54,
        "Generosity":0.18,
        "Perceptions of corruption": 0.08
    },
    {
        "countries": "Saudi Arabia",
        "HappinessRank": 28,
        "HappinessScore": 6.38,
        "GDP_per_capita": 1.40,
        "SocialSupport": 1.36,
        "Healthy life expectancy": 0.80,
        "Freedom to make life choices": 0.44,
        "Generosity": 0.08,
        "Perceptions of corruption": 0.13
    },
    {
        "countries": "Qatar",
        "HappinessRank": 29,
        "HappinessScore": 6.37,
        "GDP_per_capita": 1.68,
        "SocialSupport": 1.31,
        "Healthy life expectancy": 0.87,
        "Freedom to make life choices": 0.56,
        "Generosity": 0.22,
        "Perceptions of corruption": 0.17
    },
    {
        "countries": "Spain",
        "HappinessRank": 30,
        "HappinessScore": 6.35,
        "GDP_per_capita": "1.29",
        "SocialSupport": "1.48",
        "Healthy life expectancy": "1.06",
        "Freedom to make life choices": "0.36",
        "Generosity": "0.15",
        "Perceptions of corruption": "0.08"
    },
    {
        "countries": "Panama",
        "HappinessRank": "31",
        "HappinessScore": "6.32",
        "GDP_per_capita": "1.15",
        "SocialSupport": "1.44",
        "Healthy life expectancy": "0.91",
        "Freedom to make life choices": "0.52",
        "Generosity": "0.11",
        "Perceptions of corruption": "0.05"
    },
    {
        "countries": "Brazil",
        "HappinessRank": "32",
        "HappinessScore": "6.30",
        "GDP_per_capita": "1.00",
        "SocialSupport": "1.44",
        "Healthy life expectancy": "0.80",
        "Freedom to make life choices": "0.39",
        "Generosity": "0.10",
        "Perceptions of corruption": "0.09"
    },
    {
        "countries": "Uruguay",
        "HappinessRank": "33",
        "HappinessScore": "6.29",
        "GDP_per_capita": "1.12",
        "SocialSupport": "1.47",
        "Healthy life expectancy": "0.89",
        "Freedom to make life choices": "0.52",
        "Generosity": "0.13",
        "Perceptions of corruption": "0.15"
    },
    {
        "countries": "Singapore",
        "HappinessRank": "34",
        "HappinessScore": "6.26",
        "GDP_per_capita": "1.57",
        "SocialSupport": "1.46",
        "Healthy life expectancy": "1.14",
        "Freedom to make life choices": "0.56",
        "Generosity": "0.27",
        "Perceptions of corruption": "0.45"
    },
    {
        "countries": "El Salvador",
        "HappinessRank": "35",
        "HappinessScore": "6.25",
        "GDP_per_capita": "0.79",
        "SocialSupport": "1.24",
        "Healthy life expectancy": "0.79",
        "Freedom to make life choices": "0.43",
        "Generosity": "0.09",
        "Perceptions of corruption": "0.07"
    },
    {
        "countries": "Italy",
        "HappinessRank": "36",
        "HappinessScore": "6.22",
        "GDP_per_capita": "1.29",
        "SocialSupport": "1.49",
        "Healthy life expectancy": "1.04",
        "Freedom to make life choices": "0.23",
        "Generosity": "0.16",
        "Perceptions of corruption": "0.03"
    },
    {
        "countries": "Bahrain",
        "HappinessRank": "37",
        "HappinessScore": "6.20",
        "GDP_per_capita": "1.36",
        "SocialSupport": "1.37",
        "Healthy life expectancy": "0.87",
        "Freedom to make life choices": "0.54",
        "Generosity": "0.26",
        "Perceptions of corruption": "0.11"
    },
    {
        "countries": "Slovakia",
        "HappinessRank": "38",
        "HappinessScore": "6.20",
        "GDP_per_capita": "1.25",
        "SocialSupport": "1.50",
        "Healthy life expectancy": "0.88",
        "Freedom to make life choices": "0.33",
        "Generosity": "0.12",
        "Perceptions of corruption": "0.01"
    },
    {
        "countries": "Trinidad & Tobago",
        "HappinessRank": "39",
        "HappinessScore": "6.19",
        "GDP_per_capita": "1.23",
        "SocialSupport": "1.48",
        "Healthy life expectancy": "0.71",
        "Freedom to make life choices": "0.49",
        "Generosity": "0.19",
        "Perceptions of corruption": "0.02"
    },
    {
        "countries": "Poland",
        "HappinessRank": "40",
        "HappinessScore": "6.18",
        "GDP_per_capita": "1.21",
        "SocialSupport": "1.44",
        "Healthy life expectancy": "0.88",
        "Freedom to make life choices": "0.48",
        "Generosity": "0.12",
        "Perceptions of corruption": "0.05"
    },
    {
        "countries": "Uzbekistan",
        "HappinessRank": "41",
        "HappinessScore": "6.17",
        "GDP_per_capita": "0.75",
        "SocialSupport": "1.53",
        "Healthy life expectancy": "0.76",
        "Freedom to make life choices": "0.63",
        "Generosity": "0.32",
        "Perceptions of corruption": "0.24"
    },
    {
        "countries": "Lithuania",
        "HappinessRank": "42",
        "HappinessScore": "6.15",
        "GDP_per_capita": "1.24",
        "SocialSupport": "1.52",
        "Healthy life expectancy": "0.82",
        "Freedom to make life choices": "0.29",
        "Generosity": "0.04",
        "Perceptions of corruption": "0.04"
    },
    {
        "countries": "Colombia",
        "HappinessRank": "43",
        "HappinessScore": "6.13",
        "GDP_per_capita": "0.99",
        "SocialSupport": "1.41",
        "Healthy life expectancy": "0.84",
        "Freedom to make life choices": "0.47",
        "Generosity": "0.10",
        "Perceptions of corruption": "0.03"
    },
    {
        "countries": "Slovenia",
        "HappinessRank": "44",
        "HappinessScore": "6.12",
        "GDP_per_capita": "1.26",
        "SocialSupport": "1.52",
        "Healthy life expectancy": "0.95",
        "Freedom to make life choices": "0.56",
        "Generosity": "0.14",
        "Perceptions of corruption": "0.06"
    },
    {
        "countries": "Nicaragua",
        "HappinessRank": "45",
        "HappinessScore": "6.11",
        "GDP_per_capita": "0.69",
        "SocialSupport": "1.33",
        "Healthy life expectancy": "0.84",
        "Freedom to make life choices": "0.44",
        "Generosity": "0.20",
        "Perceptions of corruption": "0.13"
    },
    {
        "countries": "Kosovo",
        "HappinessRank": "46",
        "HappinessScore": "6.10",
        "GDP_per_capita": "0.88",
        "SocialSupport": "1.23",
        "Healthy life expectancy": "0.76",
        "Freedom to make life choices": "0.49",
        "Generosity": "0.26",
        "Perceptions of corruption": "0.01"
    },
    {
        "countries": "Argentina",
        "HappinessRank": "47",
        "HappinessScore": "6.09",
        "GDP_per_capita": "1.09",
        "SocialSupport": "1.43",
        "Healthy life expectancy": "0.88",
        "Freedom to make life choices": "0.47",
        "Generosity": "0.07",
        "Perceptions of corruption": "0.05"
    },
    {
        "countries": "Romania",
        "HappinessRank": "48",
        "HappinessScore": "6.07",
        "GDP_per_capita": "1.16",
        "SocialSupport": "1.23",
        "Healthy life expectancy": "0.83",
        "Freedom to make life choices": "0.46",
        "Generosity": "0.08",
        "Perceptions of corruption": "0.01"
    },
    {
        "countries": "Cyprus",
        "HappinessRank": "49",
        "HappinessScore": "6.05",
        "GDP_per_capita": "1.26",
        "SocialSupport": "1.22",
        "Healthy life expectancy": "1.04",
        "Freedom to make life choices": "0.41",
        "Generosity": "0.19",
        "Perceptions of corruption": "0.04"
    },
    {
        "countries": "Ecuador",
        "HappinessRank": "50",
        "HappinessScore": "6.03",
        "GDP_per_capita": "0.91",
        "SocialSupport": "1.31",
        "Healthy life expectancy": "0.87",
        "Freedom to make life choices": "0.50",
        "Generosity": "0.13",
        "Perceptions of corruption": "0.09"
    },
    {
        "countries": "Kuwait",
        "HappinessRank": "51",
        "HappinessScore": "6.02",
        "GDP_per_capita": "1.50",
        "SocialSupport": "1.32",
        "Healthy life expectancy": "0.81",
        "Freedom to make life choices": "0.49",
        "Generosity": "0.14",
        "Perceptions of corruption": "0.10"
    },
    {
        "countries": "Thailand",
        "HappinessRank": "52",
        "HappinessScore": "6.01",
        "GDP_per_capita": "1.05",
        "SocialSupport": "1.41",
        "Healthy life expectancy": "0.83",
        "Freedom to make life choices": "0.56",
        "Generosity": "0.36",
        "Perceptions of corruption": "0.03"
    },
    {
        "countries": "Latvia",
        "HappinessRank": "53",
        "HappinessScore": "5.94",
        "GDP_per_capita": "1.19",
        "SocialSupport": "1.47",
        "Healthy life expectancy": "0.81",
        "Freedom to make life choices": "0.26",
        "Generosity": "0.08",
        "Perceptions of corruption": "0.06"
    },
    {
        "countries": "South Korea",
        "HappinessRank": "54",
        "HappinessScore": "5.90",
        "GDP_per_capita": "1.30",
        "SocialSupport": "1.22",
        "Healthy life expectancy": "1.04",
        "Freedom to make life choices": "0.16",
        "Generosity": "0.18",
        "Perceptions of corruption": "0.06"
    },
    {
        "countries": "Estonia",
        "HappinessRank": "55",
        "HappinessScore": "5.89",
        "GDP_per_capita": "1.24",
        "SocialSupport": "1.53",
        "Healthy life expectancy": "0.87",
        "Freedom to make life choices": "0.50",
        "Generosity": "0.10",
        "Perceptions of corruption": "0.16"
    },
    {
        "countries": "Jamaica",
        "HappinessRank": "56",
        "HappinessScore": "5.89",
        "GDP_per_capita": "0.83",
        "SocialSupport": "1.48",
        "Healthy life expectancy": "0.83",
        "Freedom to make life choices": "0.49",
        "Generosity": "0.11",
        "Perceptions of corruption": "0.03"
    },
    {
        "countries": "Mauritius",
        "HappinessRank": "57",
        "HappinessScore": "5.89",
        "GDP_per_capita": "1.12",
        "SocialSupport": "1.40",
        "Healthy life expectancy": "0.80",
        "Freedom to make life choices": "0.50",
        "Generosity": "0.22",
        "Perceptions of corruption": "0.06"
    },
    {
        "countries": "Japan",
        "HappinessRank": "58",
        "HappinessScore": "5.89",
        "GDP_per_capita": "1.33",
        "SocialSupport": "1.42",
        "Healthy life expectancy": "1.09",
        "Freedom to make life choices": "0.45",
        "Generosity": "0.07",
        "Perceptions of corruption": "0.14"
    },
    {
        "countries": "Honduras",
        "HappinessRank": "59",
        "HappinessScore": "5.86",
        "GDP_per_capita": "0.64",
        "SocialSupport": "1.24",
        "Healthy life expectancy": "0.83",
        "Freedom to make life choices": "0.51",
        "Generosity": "0.25",
        "Perceptions of corruption": "0.08"
    },
    {
        "countries": "Kazakhstan",
        "HappinessRank": "60",
        "HappinessScore": "5.81",
        "GDP_per_capita": "1.17",
        "SocialSupport": "1.51",
        "Healthy life expectancy": "0.73",
        "Freedom to make life choices": "0.41",
        "Generosity": "0.15",
        "Perceptions of corruption": "0.10"
    },
    {
        "countries": "Bolivia",
        "HappinessRank": "61",
        "HappinessScore": "5.78",
        "GDP_per_capita": "0.78",
        "SocialSupport": "1.21",
        "Healthy life expectancy": "0.71",
        "Freedom to make life choices": "0.51",
        "Generosity": "0.14",
        "Perceptions of corruption": "0.06"
    },
    {
        "countries": "Hungary",
        "HappinessRank": "62",
        "HappinessScore": "5.76",
        "GDP_per_capita": "1.20",
        "SocialSupport": "1.41",
        "Healthy life expectancy": "0.83",
        "Freedom to make life choices": "0.20",
        "Generosity": "0.08",
        "Perceptions of corruption": "0.02"
    },
    {
        "countries": "Paraguay",
        "HappinessRank": "63",
        "HappinessScore": "5.74",
        "GDP_per_capita": "0.86",
        "SocialSupport": "1.48",
        "Healthy life expectancy": "0.78",
        "Freedom to make life choices": "0.51",
        "Generosity": "0.18",
        "Perceptions of corruption": "0.08"
    },
    {
        "countries": "Northern Cyprus",
        "HappinessRank": "64",
        "HappinessScore": "5.72",
        "GDP_per_capita": "1.26",
        "SocialSupport": "1.25",
        "Healthy life expectancy": "1.04",
        "Freedom to make life choices": "0.42",
        "Generosity": "0.19",
        "Perceptions of corruption": "0.16"
    },
    {
        "countries": "Peru",
        "HappinessRank": "65",
        "HappinessScore": "5.70",
        "GDP_per_capita": "0.96",
        "SocialSupport": "1.27",
        "Healthy life expectancy": "0.85",
        "Freedom to make life choices": "0.46",
        "Generosity": "0.08",
        "Perceptions of corruption": "0.03"
    },
    {
        "countries": "Portugal",
        "HappinessRank": "66",
        "HappinessScore": "5.69",
        "GDP_per_capita": "1.22",
        "SocialSupport": "1.43",
        "Healthy life expectancy": "1.00",
        "Freedom to make life choices": "0.51",
        "Generosity": "0.05",
        "Perceptions of corruption": "0.03"
    },
    {
        "countries": "Pakistan",
        "HappinessRank": "67",
        "HappinessScore": "5.65",
        "GDP_per_capita": "0.68",
        "SocialSupport": "0.89",
        "Healthy life expectancy": "0.54",
        "Freedom to make life choices": "0.31",
        "Generosity": "0.22",
        "Perceptions of corruption": "0.10"
    },
    {
        "countries": "Russia",
        "HappinessRank": "68",
        "HappinessScore": "5.65",
        "GDP_per_capita": "1.18",
        "SocialSupport": "1.45",
        "Healthy life expectancy": "0.73",
        "Freedom to make life choices": "0.33",
        "Generosity": "0.08",
        "Perceptions of corruption": "0.03"
    },
    {
        "countries": "Philippines",
        "HappinessRank": "69",
        "HappinessScore": "5.63",
        "GDP_per_capita": "0.81",
        "SocialSupport": "1.29",
        "Healthy life expectancy": "0.66",
        "Freedom to make life choices": "0.56",
        "Generosity": "0.12",
        "Perceptions of corruption": "0.11"
    },
    {
        "countries": "Serbia",
        "HappinessRank": "70",
        "HappinessScore": "5.60",
        "GDP_per_capita": "1.00",
        "SocialSupport": "1.38",
        "Healthy life expectancy": "0.85",
        "Freedom to make life choices": "0.28",
        "Generosity": "0.14",
        "Perceptions of corruption": "0.04"
    },
    {
        "countries": "Moldova",
        "HappinessRank": "71",
        "HappinessScore": "5.53",
        "GDP_per_capita": "0.69",
        "SocialSupport": "1.33",
        "Healthy life expectancy": "0.74",
        "Freedom to make life choices": "0.25",
        "Generosity": "0.18",
        "Perceptions of corruption": "0.00"
    },
    {
        "countries": "Libya",
        "HappinessRank": "72",
        "HappinessScore": "5.53",
        "GDP_per_capita": "1.04",
        "SocialSupport": "1.30",
        "Healthy life expectancy": "0.67",
        "Freedom to make life choices": "0.42",
        "Generosity": "0.13",
        "Perceptions of corruption": "0.15"
    },
    {
        "countries": "Montenegro",
        "HappinessRank": "73",
        "HappinessScore": "5.52",
        "GDP_per_capita": "1.05",
        "SocialSupport": "1.36",
        "Healthy life expectancy": "0.87",
        "Freedom to make life choices": "0.20",
        "Generosity": "0.14",
        "Perceptions of corruption": "0.08"
    },
    {
        "countries": "Tajikistan",
        "HappinessRank": "74",
        "HappinessScore": "5.47",
        "GDP_per_capita": "0.49",
        "SocialSupport": "1.10",
        "Healthy life expectancy": "0.72",
        "Freedom to make life choices": "0.39",
        "Generosity": "0.23",
        "Perceptions of corruption": "0.14"
    },
    {
        "countries": "Croatia",
        "HappinessRank": "75",
        "HappinessScore": "5.43",
        "GDP_per_capita": "1.16",
        "SocialSupport": "1.27",
        "Healthy life expectancy": "0.91",
        "Freedom to make life choices": "0.30",
        "Generosity": "0.12",
        "Perceptions of corruption": "0.02"
    },
    {
        "countries": "Hong Kong",
        "HappinessRank": "76",
        "HappinessScore": "5.43",
        "GDP_per_capita": "1.44",
        "SocialSupport": "1.28",
        "Healthy life expectancy": "1.12",
        "Freedom to make life choices": "0.44",
        "Generosity": "0.26",
        "Perceptions of corruption": "0.29"
    },
    {
        "countries": "Dominican Republic",
        "HappinessRank": "77",
        "HappinessScore": "5.43",
        "GDP_per_capita": "1.02",
        "SocialSupport": "1.40",
        "Healthy life expectancy": "0.78",
        "Freedom to make life choices": "0.50",
        "Generosity": "0.11",
        "Perceptions of corruption": "0.10"
    },
    {
        "countries": "Bosnia and Herzegovina",
        "HappinessRank": "78",
        "HappinessScore": "5.39",
        "GDP_per_capita": "0.95",
        "SocialSupport": "1.21",
        "Healthy life expectancy": "0.85",
        "Freedom to make life choices": "0.21",
        "Generosity": "0.26",
        "Perceptions of corruption": "0.01"
    },
    {
        "countries": "Turkey",
        "HappinessRank": "79",
        "HappinessScore": "5.37",
        "GDP_per_capita": "1.18",
        "SocialSupport": "1.36",
        "Healthy life expectancy": "0.81",
        "Freedom to make life choices": "0.20",
        "Generosity": "0.08",
        "Perceptions of corruption": "0.11"
    },
    {
        "countries": "Malaysia",
        "HappinessRank": "80",
        "HappinessScore": "5.34",
        "GDP_per_capita": "1.22",
        "SocialSupport": "1.17",
        "Healthy life expectancy": "0.83",
        "Freedom to make life choices": "0.51",
        "Generosity": "0.26",
        "Perceptions of corruption": "0.02"
    },
    {
        "countries": "Belarus",
        "HappinessRank": "81",
        "HappinessScore": "5.32",
        "GDP_per_capita": "1.07",
        "SocialSupport": "1.47",
        "Healthy life expectancy": "0.79",
        "Freedom to make life choices": "0.24",
        "Generosity": "0.09",
        "Perceptions of corruption": "0.14"
    },
    {
        "countries": "Greece",
        "HappinessRank": "82",
        "HappinessScore": "5.29",
        "GDP_per_capita": "1.18",
        "SocialSupport": "1.16",
        "Healthy life expectancy": "1.00",
        "Freedom to make life choices": "0.07",
        "Generosity": "0.00",
        "Perceptions of corruption": "0.03"
    },
    {
        "countries": "Mongolia",
        "HappinessRank": "83",
        "HappinessScore": "5.29",
        "GDP_per_capita": "0.95",
        "SocialSupport": "1.53",
        "Healthy life expectancy": "0.67",
        "Freedom to make life choices": "0.32",
        "Generosity": "0.24",
        "Perceptions of corruption": "0.04"
    },
    {
        "countries": "North Macedonia",
        "HappinessRank": "84",
        "HappinessScore": "5.27",
        "GDP_per_capita": "0.98",
        "SocialSupport": "1.29",
        "Healthy life expectancy": "0.84",
        "Freedom to make life choices": "0.35",
        "Generosity": "0.19",
        "Perceptions of corruption": "0.03"
    },
    {
        "countries": "Nigeria",
        "HappinessRank": "85",
        "HappinessScore": "5.27",
        "GDP_per_capita": "0.70",
        "SocialSupport": "1.11",
        "Healthy life expectancy": "0.25",
        "Freedom to make life choices": "0.43",
        "Generosity": "0.22",
        "Perceptions of corruption": "0.04"
    },
    {
        "countries": "Kyrgyzstan",
        "HappinessRank": "86",
        "HappinessScore": "5.26",
        "GDP_per_capita": "0.55",
        "SocialSupport": "1.44",
        "Healthy life expectancy": "0.72",
        "Freedom to make life choices": "0.51",
        "Generosity": "0.30",
        "Perceptions of corruption": "0.02"
    },
    {
        "countries": "Turkmenistan",
        "HappinessRank": "87",
        "HappinessScore": "5.25",
        "GDP_per_capita": "1.05",
        "SocialSupport": "1.54",
        "Healthy life expectancy": "0.66",
        "Freedom to make life choices": "0.39",
        "Generosity": "0.24",
        "Perceptions of corruption": "0.03"
    },
    {
        "countries": "Algeria",
        "HappinessRank": "88",
        "HappinessScore": "5.21",
        "GDP_per_capita": "1.00",
        "SocialSupport": "1.16",
        "Healthy life expectancy": "0.79",
        "Freedom to make life choices": "0.09",
        "Generosity": "0.07",
        "Perceptions of corruption": "0.11"
    },
    {
        "countries": "Morocco",
        "HappinessRank": "89",
        "HappinessScore": "5.21",
        "GDP_per_capita": "0.80",
        "SocialSupport": "0.78",
        "Healthy life expectancy": "0.78",
        "Freedom to make life choices": "0.42",
        "Generosity": "0.04",
        "Perceptions of corruption": "0.08"
    },
    {
        "countries": "Azerbaijan",
        "HappinessRank": "90",
        "HappinessScore": "5.21",
        "GDP_per_capita": "1.04",
        "SocialSupport": "1.15",
        "Healthy life expectancy": "0.77",
        "Freedom to make life choices": "0.35",
        "Generosity": "0.04",
        "Perceptions of corruption": "0.18"
    },
    {
        "countries": "Lebanon",
        "HappinessRank": "91",
        "HappinessScore": "5.20",
        "GDP_per_capita": "0.99",
        "SocialSupport": "1.22",
        "Healthy life expectancy": "0.82",
        "Freedom to make life choices": "0.22",
        "Generosity": "0.17",
        "Perceptions of corruption": "0.03"
    },
    {
        "countries": "Indonesia",
        "HappinessRank": "92",
        "HappinessScore": "5.19",
        "GDP_per_capita": "0.93",
        "SocialSupport": "1.20",
        "Healthy life expectancy": "0.66",
        "Freedom to make life choices": "0.49",
        "Generosity": "0.50",
        "Perceptions of corruption": "0.03"
    },
    {
        "countries": "China",
        "HappinessRank": "93",
        "HappinessScore": "5.19",
        "GDP_per_capita": "1.03",
        "SocialSupport": "1.13",
        "Healthy life expectancy": "0.89",
        "Freedom to make life choices": "0.52",
        "Generosity": "0.06",
        "Perceptions of corruption": "0.10"
    },
    {
        "countries": "Vietnam",
        "HappinessRank": "94",
        "HappinessScore": "5.18",
        "GDP_per_capita": "0.74",
        "SocialSupport": "1.35",
        "Healthy life expectancy": "0.85",
        "Freedom to make life choices": "0.54",
        "Generosity": "0.15",
        "Perceptions of corruption": "0.07"
    },
    {
        "countries": "Bhutan",
        "HappinessRank": "95",
        "HappinessScore": "5.08",
        "GDP_per_capita": "0.81",
        "SocialSupport": "1.32",
        "Healthy life expectancy": "0.60",
        "Freedom to make life choices": "0.46",
        "Generosity": "0.37",
        "Perceptions of corruption": "0.17"
    },
    {
        "countries": "Cameroon",
        "HappinessRank": "96",
        "HappinessScore": "5.04",
        "GDP_per_capita": "0.55",
        "SocialSupport": "0.91",
        "Healthy life expectancy": "0.33",
        "Freedom to make life choices": "0.38",
        "Generosity": "0.19",
        "Perceptions of corruption": "0.04"
    },
    {
        "countries": "Bulgaria",
        "HappinessRank": "97",
        "HappinessScore": "5.01",
        "GDP_per_capita": "1.09",
        "SocialSupport": "1.51",
        "Healthy life expectancy": "0.82",
        "Freedom to make life choices": "0.31",
        "Generosity": "0.08",
        "Perceptions of corruption": "0.00"
    },
    {
        "countries": "Ghana",
        "HappinessRank": "98",
        "HappinessScore": "5.00",
        "GDP_per_capita": "0.61",
        "SocialSupport": "0.87",
        "Healthy life expectancy": "0.49",
        "Freedom to make life choices": "0.38",
        "Generosity": "0.25",
        "Perceptions of corruption": "0.04"
    },
    {
        "countries": "Ivory Coast",
        "HappinessRank": "99",
        "HappinessScore": "4.94",
        "GDP_per_capita": "0.57",
        "SocialSupport": "0.81",
        "Healthy life expectancy": "0.23",
        "Freedom to make life choices": "0.35",
        "Generosity": "0.15",
        "Perceptions of corruption": "0.09"
    },
    {
        "countries": "Nepal",
        "HappinessRank": "100",
        "HappinessScore": "4.91",
        "GDP_per_capita": "0.45",
        "SocialSupport": "1.23",
        "Healthy life expectancy": "0.68",
        "Freedom to make life choices": "0.44",
        "Generosity": "0.29",
        "Perceptions of corruption": "0.09"
    },
    {
        "countries": "Jordan",
        "HappinessRank": "101",
        "HappinessScore": "4.91",
        "GDP_per_capita": "0.84",
        "SocialSupport": "1.23",
        "Healthy life expectancy": "0.82",
        "Freedom to make life choices": "0.38",
        "Generosity": "0.11",
        "Perceptions of corruption": "0.13"
    },
    {
        "countries": "Benin",
        "HappinessRank": "102",
        "HappinessScore": "4.88",
        "GDP_per_capita": "0.39",
        "SocialSupport": "0.44",
        "Healthy life expectancy": "0.40",
        "Freedom to make life choices": "0.35",
        "Generosity": "0.18",
        "Perceptions of corruption": "0.08"
    },
    {
        "countries": "Congo (Brazzaville)",
        "HappinessRank": "103",
        "HappinessScore": "4.81",
        "GDP_per_capita": "0.67",
        "SocialSupport": "0.80",
        "Healthy life expectancy": "0.51",
        "Freedom to make life choices": "0.37",
        "Generosity": "0.11",
        "Perceptions of corruption": "0.09"
    },
    {
        "countries": "Gabon",
        "HappinessRank": "104",
        "HappinessScore": "4.80",
        "GDP_per_capita": "1.06",
        "SocialSupport": "1.18",
        "Healthy life expectancy": "0.57",
        "Freedom to make life choices": "0.30",
        "Generosity": "0.04",
        "Perceptions of corruption": "0.06"
    },
    {
        "countries": "Laos",
        "HappinessRank": "105",
        "HappinessScore": "4.80",
        "GDP_per_capita": "0.76",
        "SocialSupport": "1.03",
        "Healthy life expectancy": "0.55",
        "Freedom to make life choices": "0.55",
        "Generosity": "0.27",
        "Perceptions of corruption": "0.16"
    },
    {
        "countries": "South Africa",
        "HappinessRank": "106",
        "HappinessScore": "4.72",
        "GDP_per_capita": "0.96",
        "SocialSupport": "1.35",
        "Healthy life expectancy": "0.47",
        "Freedom to make life choices": "0.39",
        "Generosity": "0.13",
        "Perceptions of corruption": "0.06"
    },
    {
        "countries": "Albania",
        "HappinessRank": "107",
        "HappinessScore": "4.72",
        "GDP_per_capita": "0.95",
        "SocialSupport": "0.85",
        "Healthy life expectancy": "0.87",
        "Freedom to make life choices": "0.38",
        "Generosity": "0.18",
        "Perceptions of corruption": "0.03"
    },
    {
        "countries": "Venezuela",
        "HappinessRank": "108",
        "HappinessScore": "4.71",
        "GDP_per_capita": "0.96",
        "SocialSupport": "1.43",
        "Healthy life expectancy": "0.81",
        "Freedom to make life choices": "0.15",
        "Generosity": "0.06",
        "Perceptions of corruption": "0.05"
    },
    {
        "countries": "Cambodia",
        "HappinessRank": "109",
        "HappinessScore": "4.70",
        "GDP_per_capita": "0.57",
        "SocialSupport": "1.12",
        "Healthy life expectancy": "0.64",
        "Freedom to make life choices": "0.61",
        "Generosity": "0.23",
        "Perceptions of corruption": "0.06"
    },
    {
        "countries": "Palestinian Territories",
        "HappinessRank": "110",
        "HappinessScore": "4.70",
        "GDP_per_capita": "0.66",
        "SocialSupport": "1.25",
        "Healthy life expectancy": "0.67",
        "Freedom to make life choices": "0.23",
        "Generosity": "0.10",
        "Perceptions of corruption": "0.07"
    },
    {
        "countries": "Senegal",
        "HappinessRank": "111",
        "HappinessScore": "4.68",
        "GDP_per_capita": "0.45",
        "SocialSupport": "1.13",
        "Healthy life expectancy": "0.57",
        "Freedom to make life choices": "0.29",
        "Generosity": "0.15",
        "Perceptions of corruption": "0.07"
    },
    {
        "countries": "Somalia",
        "HappinessRank": "112",
        "HappinessScore": "4.67",
        "GDP_per_capita": "0.00",
        "SocialSupport": "0.70",
        "Healthy life expectancy": "0.27",
        "Freedom to make life choices": "0.56",
        "Generosity": "0.24",
        "Perceptions of corruption": "0.27"
    },
    {
        "countries": "Namibia",
        "HappinessRank": "113",
        "HappinessScore": "4.64",
        "GDP_per_capita": "0.88",
        "SocialSupport": "1.31",
        "Healthy life expectancy": "0.48",
        "Freedom to make life choices": "0.40",
        "Generosity": "0.07",
        "Perceptions of corruption": "0.06"
    },
    {
        "countries": "Niger",
        "HappinessRank": "114",
        "HappinessScore": "4.63",
        "GDP_per_capita": "0.14",
        "SocialSupport": "0.77",
        "Healthy life expectancy": "0.37",
        "Freedom to make life choices": "0.32",
        "Generosity": "0.19",
        "Perceptions of corruption": "0.10"
    },
    {
        "countries": "Burkina Faso",
        "HappinessRank": "115",
        "HappinessScore": "4.59",
        "GDP_per_capita": "0.33",
        "SocialSupport": "1.06",
        "Healthy life expectancy": "0.38",
        "Freedom to make life choices": "0.26",
        "Generosity": "0.18",
        "Perceptions of corruption": "0.11"
    },
    {
        "countries": "Armenia",
        "HappinessRank": "116",
        "HappinessScore": "4.56",
        "GDP_per_capita": "0.85",
        "SocialSupport": "1.06",
        "Healthy life expectancy": "0.82",
        "Freedom to make life choices": "0.28",
        "Generosity": "0.10",
        "Perceptions of corruption": "0.06"
    },
    {
        "countries": "Iran",
        "HappinessRank": "117",
        "HappinessScore": "4.55",
        "GDP_per_capita": "1.10",
        "SocialSupport": "0.84",
        "Healthy life expectancy": "0.79",
        "Freedom to make life choices": "0.31",
        "Generosity": "0.27",
        "Perceptions of corruption": "0.13"
    },
    {
        "countries": "Guinea",
        "HappinessRank": "118",
        "HappinessScore": "4.53",
        "GDP_per_capita": "0.38",
        "SocialSupport": "0.83",
        "Healthy life expectancy": "0.38",
        "Freedom to make life choices": "0.33",
        "Generosity": "0.21",
        "Perceptions of corruption": "0.09"
    },
    {
        "countries": "Georgia",
        "HappinessRank": "119",
        "HappinessScore": "4.52",
        "GDP_per_capita": "0.89",
        "SocialSupport": "0.67",
        "Healthy life expectancy": "0.75",
        "Freedom to make life choices": "0.35",
        "Generosity": "0.04",
        "Perceptions of corruption": "0.16"
    },
    {
        "countries": "Gambia",
        "HappinessRank": "120",
        "HappinessScore": "4.52",
        "GDP_per_capita": "0.31",
        "SocialSupport": "0.94",
        "Healthy life expectancy": "0.43",
        "Freedom to make life choices": "0.38",
        "Generosity": "0.27",
        "Perceptions of corruption": "0.17"
    },
    {
        "countries": "Kenya",
        "HappinessRank": "121",
        "HappinessScore": "4.51",
        "GDP_per_capita": "0.51",
        "SocialSupport": "0.98",
        "Healthy life expectancy": "0.58",
        "Freedom to make life choices": "0.43",
        "Generosity": "0.37",
        "Perceptions of corruption": "0.05"
    },
    {
        "countries": "Mauritania",
        "HappinessRank": "122",
        "HappinessScore": "4.49",
        "GDP_per_capita": "0.57",
        "SocialSupport": "1.17",
        "Healthy life expectancy": "0.49",
        "Freedom to make life choices": "0.07",
        "Generosity": "0.11",
        "Perceptions of corruption": "0.09"
    },
    {
        "countries": "Mozambique",
        "HappinessRank": "123",
        "HappinessScore": "4.47",
        "GDP_per_capita": "0.20",
        "SocialSupport": "0.99",
        "Healthy life expectancy": "0.39",
        "Freedom to make life choices": "0.49",
        "Generosity": "0.20",
        "Perceptions of corruption": "0.14"
    },
    {
        "countries": "Tunisia",
        "HappinessRank": "124",
        "HappinessScore": "4.46",
        "GDP_per_capita": "0.92",
        "SocialSupport": "1.00",
        "Healthy life expectancy": "0.82",
        "Freedom to make life choices": "0.17",
        "Generosity": "0.06",
        "Perceptions of corruption": "0.06"
    },
    {
        "countries": "Bangladesh",
        "HappinessRank": "125",
        "HappinessScore": "4.46",
        "GDP_per_capita": "0.56",
        "SocialSupport": "0.93",
        "Healthy life expectancy": "0.72",
        "Freedom to make life choices": "0.53",
        "Generosity": "0.17",
        "Perceptions of corruption": "0.14"
    },
    {
        "countries": "Iraq",
        "HappinessRank": "126",
        "HappinessScore": "4.44",
        "GDP_per_capita": "1.04",
        "SocialSupport": "0.98",
        "Healthy life expectancy": "0.57",
        "Freedom to make life choices": "0.24",
        "Generosity": "0.15",
        "Perceptions of corruption": "0.09"
    },
    {
        "countries": "Congo (Kinshasa)",
        "HappinessRank": "127",
        "HappinessScore": "4.42",
        "GDP_per_capita": "0.09",
        "SocialSupport": "1.13",
        "Healthy life expectancy": "0.36",
        "Freedom to make life choices": "0.27",
        "Generosity": "0.21",
        "Perceptions of corruption": "0.05"
    },
    {
        "countries": "Mali",
        "HappinessRank": "128",
        "HappinessScore": "4.39",
        "GDP_per_capita": "0.39",
        "SocialSupport": "1.11",
        "Healthy life expectancy": "0.31",
        "Freedom to make life choices": "0.33",
        "Generosity": "0.15",
        "Perceptions of corruption": "0.05"
    },
    {
        "countries": "Sierra Leone",
        "HappinessRank": "129",
        "HappinessScore": "4.37",
        "GDP_per_capita": "0.27",
        "SocialSupport": "0.84",
        "Healthy life expectancy": "0.24",
        "Freedom to make life choices": "0.31",
        "Generosity": "0.25",
        "Perceptions of corruption": "0.05"
    },
    {
        "countries": "Sri Lanka",
        "HappinessRank": "130",
        "HappinessScore": "4.37",
        "GDP_per_capita": "0.95",
        "SocialSupport": "1.27",
        "Healthy life expectancy": "0.83",
        "Freedom to make life choices": "0.47",
        "Generosity": "0.24",
        "Perceptions of corruption": "0.05"
    },
    {
        "countries": "Myanmar",
        "HappinessRank": "131",
        "HappinessScore": "4.36",
        "GDP_per_capita": "0.71",
        "SocialSupport": "1.18",
        "Healthy life expectancy": "0.56",
        "Freedom to make life choices": "0.53",
        "Generosity": "0.57",
        "Perceptions of corruption": "0.17"
    },
    {
        "countries": "Chad",
        "HappinessRank": "132",
        "HappinessScore": "4.35",
        "GDP_per_capita": "0.35",
        "SocialSupport": "0.77",
        "Healthy life expectancy": "0.19",
        "Freedom to make life choices": "0.17",
        "Generosity": "0.20",
        "Perceptions of corruption": "0.08"
    },
    {
        "countries": "Ukraine",
        "HappinessRank": "133",
        "HappinessScore": "4.33",
        "GDP_per_capita": "0.82",
        "SocialSupport": "1.39",
        "Healthy life expectancy": "0.74",
        "Freedom to make life choices": "0.18",
        "Generosity": "0.19",
        "Perceptions of corruption": "0.01"
    },
    {
        "countries": "Ethiopia",
        "HappinessRank": "134",
        "HappinessScore": "4.29",
        "GDP_per_capita": "0.34",
        "SocialSupport": "1.03",
        "Healthy life expectancy": "0.53",
        "Freedom to make life choices": "0.34",
        "Generosity": "0.21",
        "Perceptions of corruption": "0.10"
    },
    {
        "countries": "Swaziland",
        "HappinessRank": "135",
        "HappinessScore": "4.21",
        "GDP_per_capita": "0.81",
        "SocialSupport": "1.15",
        "Healthy life expectancy": "0.00",
        "Freedom to make life choices": "0.31",
        "Generosity": "0.07",
        "Perceptions of corruption": "0.14"
    },
    {
        "countries": "Uganda",
        "HappinessRank": "136",
        "HappinessScore": "4.19",
        "GDP_per_capita": "0.33",
        "SocialSupport": "1.07",
        "Healthy life expectancy": "0.44",
        "Freedom to make life choices": "0.36",
        "Generosity": "0.25",
        "Perceptions of corruption": "0.06"
    },
    {
        "countries": "Egypt",
        "HappinessRank": "137",
        "HappinessScore": "4.17",
        "GDP_per_capita": "0.91",
        "SocialSupport": "1.04",
        "Healthy life expectancy": "0.64",
        "Freedom to make life choices": "0.24",
        "Generosity": "0.08",
        "Perceptions of corruption": "0.07"
    },
    {
        "countries": "Zambia",
        "HappinessRank": "138",
        "HappinessScore": "4.11",
        "GDP_per_capita": "0.58",
        "SocialSupport": "1.06",
        "Healthy life expectancy": "0.43",
        "Freedom to make life choices": "0.43",
        "Generosity": "0.25",
        "Perceptions of corruption": "0.09"
    },
    {
        "countries": "Togo",
        "HappinessRank": "139",
        "HappinessScore": "4.09",
        "GDP_per_capita": "0.28",
        "SocialSupport": "0.57",
        "Healthy life expectancy": "0.41",
        "Freedom to make life choices": "0.29",
        "Generosity": "0.18",
        "Perceptions of corruption": "0.09"
    },
    {
        "countries": "India",
        "HappinessRank": "140",
        "HappinessScore": "4.02",
        "GDP_per_capita": "0.76",
        "SocialSupport": "0.77",
        "Healthy life expectancy": "0.59",
        "Freedom to make life choices": "0.50",
        "Generosity": "0.20",
        "Perceptions of corruption": "0.09"
    },
    {
        "countries": "Liberia",
        "HappinessRank": "141",
        "HappinessScore": "3.98",
        "GDP_per_capita": "0.07",
        "SocialSupport": "0.92",
        "Healthy life expectancy": "0.44",
        "Freedom to make life choices": "0.37",
        "Generosity": "0.23",
        "Perceptions of corruption": "0.03"
    },
    {
        "countries": "Comoros",
        "HappinessRank": "142",
        "HappinessScore": "3.97",
        "GDP_per_capita": "0.27",
        "SocialSupport": "0.76",
        "Healthy life expectancy": "0.51",
        "Freedom to make life choices": "0.14",
        "Generosity": "0.28",
        "Perceptions of corruption": "0.08"
    },
    {
        "countries": "Madagascar",
        "HappinessRank": "143",
        "HappinessScore": "3.93",
        "GDP_per_capita": "0.27",
        "SocialSupport": "0.92",
        "Healthy life expectancy": "0.56",
        "Freedom to make life choices": "0.15",
        "Generosity": "0.17",
        "Perceptions of corruption": "0.04"
    },
    {
        "countries": "Lesotho",
        "HappinessRank": "144",
        "HappinessScore": "3.80",
        "GDP_per_capita": "0.49",
        "SocialSupport": "1.17",
        "Healthy life expectancy": "0.17",
        "Freedom to make life choices": "0.36",
        "Generosity": "0.11",
        "Perceptions of corruption": "0.09"
    },
    {
        "countries": "Burundi",
        "HappinessRank": "145",
        "HappinessScore": 3.78,
        "GDP_per_capita": 0.05,
        "SocialSupport": 0.45,
        "Healthy life expectancy": 0.38,
        "Freedom to make life choices": 0.22,
        "Generosity": 0.18,
        "Perceptions of corruption": 0.18
    },
    {
        "countries": "Zimbabwe",
        "HappinessRank": 146,
        "HappinessScore": 3.66,
        "GDP_per_capita": 0.37,
        "SocialSupport": 1.11,
        "Healthy life expectancy": 0.43,
        "Freedom to make life choices": 0.36,
        "Generosity": 0.15,
        "Perceptions of corruption": 0.09
    },
    {
        "countries": "Haiti",
        "HappinessRank": 147,
        "HappinessScore": 3.60,
        "GDP_per_capita": 0.32,
        "SocialSupport": 0.69,
        "Healthy life expectancy": 0.45,
        "Freedom to make life choices": 0.03,
        "Generosity": 0.42,
        "Perceptions of corruption": 0.11
    },
    {
        "countries": "Botswana",
        "HappinessRank": 148,
        "HappinessScore": 3.49,
        "GDP_per_capita": 1.04,
        "SocialSupport": 1.15,
        "Healthy life expectancy": 0.54,
        "Freedom to make life choices": 0.46,
        "Generosity": 0.03,
        "Perceptions of corruption": 0.10
    },
    {
        "countries": "Syria",
        "HappinessRank": 149,
        "HappinessScore": 3.46,
        "GDP_per_capita": 0.62,
        "SocialSupport": 0.38,
        "Healthy life expectancy": 0.44,
        "Freedom to make life choices": 0.01,
        "Generosity": 0.33,
        "Perceptions of corruption": 0.14
    },
    {
        "countries": "Malawi",
        "HappinessRank": 150,
        "HappinessScore": 3.41,
        "GDP_per_capita": 0.19,
        "SocialSupport": 0.56,
        "Healthy life expectancy": 0.50,
        "Freedom to make life choices": 0.44,
        "Generosity": 0.22,
        "Perceptions of corruption": 0.09
    },
    {
        "countries": "Yemen",
        "HappinessRank": 151,
        "HappinessScore": 3.38,
        "GDP_per_capita": 0.29,
        "SocialSupport": 1.16,
        "Healthy life expectancy": 0.46,
        "Freedom to make life choices": 0.14,
        "Generosity": 0.11,
        "Perceptions of corruption": 0.08
    },
    {
        "countries": "Rwanda",
        "HappinessRank": 152,
        "HappinessScore": 3.33,
        "GDP_per_capita": 0.36,
        "SocialSupport": 0.71,
        "Healthy life expectancy": 0.61,
        "Freedom to make life choices": 0.56,
        "Generosity": 0.22,
        "Perceptions of corruption": 0.41
    },
    {
        "countries": "Tanzania",
        "HappinessRank": 153,
        "HappinessScore": 3.23,
        "GDP_per_capita": 0.48,
        "SocialSupport":0.89,
        "Healthy life expectancy": 0.50,
        "Freedom to make life choices": 0.42,
        "Generosity": 0.28,
        "Perceptions of corruption": 0.15
    },
    {
        "countries": "Afghanistan",
        "HappinessRank": 154,
        "HappinessScore": 3.20,
        "GDP_per_capita": 0.35,
        "SocialSupport": 0.52,
        "Healthy life expectancy": 0.36,
        "Freedom to make life choices": 0.00,
        "Generosity": 0.16,
        "Perceptions of corruption": 0.03
    },
    {
        "countries": "Central African Republic",
        "HappinessRank": 155,
        "HappinessScore": 3.08,
        "GDP_per_capita": 0.03,
        "SocialSupport": 0.00,
        "Healthy life expectancy": 0.11,
        "Freedom to make life choices":0.23,
        "Generosity": 0.24,
        "Perceptions of corruption": 0.04
    },
    {
        "countries": "South Sudan",
        "HappinessRank": 156,
        "HappinessScore": 2.85,
        "GDP_per_capita": 0.31,
        "SocialSupport": 0.58,
        "Healthy life expectancy": 0.30,
        "Freedom to make life choices": 0.01,
        "Generosity": 0.20,
        "Perceptions of corruption": 0.09
    }
]
}